{"stations": 10, "periods": 10, "jobs": 80, "passengers": 1000, "routes": 3, "coords": [[0.9576469064369303, -0.11797757311898834], [-0.40501283769223134, -0.7886917540070408], [-0.011369399898758238, 0.15365229481892426], [-0.5845857397499298, -0.038410369045274693], [0.3594695229321427, 0.7578910699885493], [-0.5112302827035068, 0.6714780763232892], [0.08361634468644442, -0.5256138739988385], [0.2608522103388367, 0.48085196203734426], [0.5765910506178735, -0.7013648330060396], [-0.4615779762978745, -0.7641158249310043]], "pi": {"1": 1, "2": 2, "3": 1, "4": 1, "5": 1, "6": 2, "7": 1, "8": 2, "9": 2, "10": 2, "11": 2, "12": 2, "13": 1, "14": 1, "15": 2, "16": 1, "17": 1, "18": 2, "19": 2, "20": 2, "21": 2, "22": 1, "23": 2, "24": 1, "25": 1, "26": 1, "27": 2, "28": 2, "29": 2, "30": 1, "31": 2, "32": 1, "33": 2, "34": 1, "35": 1, "36": 1, "37": 1, "38": 2, "39": 2, "40": 2, "41": 2, "42": 1, "43": 1, "44": 2, "45": 1, "46": 2, "47": 2, "48": 1, "49": 1, "50": 1, "51": 2, "52": 2, "53": 1, "54": 1, "55": 2, "56": 1, "57": 1, "58": 2, "59": 1, "60": 1, "61": 1, "62": 2, "63": 1, "64": 2, "65": 1, "66": 2, "67": 1, "68": 1, "69": 1, "70": 2, "71": 1, "72": 2, "73": 1, "74": 1, "75": 1, "76": 1, "77": 2, "78": 2, "79": 2, "80": 1}, "Aj": {"1": [[4, 5]], "2": [[3, 9]], "3": [[2, 3]], "4": [[1, 4]], "5": [[1, 10]], "6": [[1, 8]], "7": [[1, 4]], "8": [[2, 8]], "9": [[4, 5]], "10": [[3, 9]], "11": [[6, 8]], "12": [[4, 6]], "13": [[4, 10]], "14": [[3, 10]], "15": [[3, 6]], "16": [[6, 9]], "17": [[6, 7]], "18": [[7, 10]], "19": [[5, 8]], "20": [[3, 10]], "21": [[7, 9]], "22": [[4, 10]], "23": [[2, 7]], "24": [[1, 8]], "25": [[3, 9]], "26": [[1, 9]], "27": [[2, 9]], "28": [[7, 8]], "29": [[8, 9]], "30": [[8, 9]], "31": [[1, 5]], "32": [[1, 5]], "33": [[5, 8]], "34": [[4, 5]], "35": [[4, 6]], "36": [[4, 9]], "37": [[4, 10]], "38": [[5, 10]], "39": [[5, 6]], "40": [[5, 9]], "41": [[1, 6]], "42": [[3, 8]], "43": [[4, 9]], "44": [[4, 7]], "45": [[1, 7]], "46": [[4, 7]], "47": [[1, 9]], "48": [[1, 5]], "49": [[3, 10]], "50": [[4, 10]], "51": [[3, 5]], "52": [[3, 4]], "53": [[3, 5]], "54": [[4, 8]], "55": [[4, 5]], "56": [[4, 6]], "57": [[1, 4]], "58": [[9, 10]], "59": [[1, 2]], "60": [[2, 9]], "61": [[6, 10]], "62": [[2, 5]], "63": [[8, 9]], "64": [[3, 10]], "65": [[1, 2]], "66": [[5, 6]], "67": [[2, 10]], "68": [[1, 9]], "69": [[5, 10]], "70": [[6, 9]], "71": [[3, 8]], "72": [[6, 9]], "73": [[2, 10]], "74": [[1, 2]], "75": [[3, 8]], "76": [[8, 10]], "77": [[2, 3]], "78": [[1, 4]], "79": [[1, 3]], "80": [[3, 8]]}, "C": [], "tau": {"(1, 2)": 1, "(1, 3)": 0, "(1, 4)": 1, "(1, 5)": 1, "(1, 6)": 0, "(1, 7)": 1, "(1, 8)": 1, "(1, 9)": 0, "(1, 10)": 0, "(2, 3)": 0, "(2, 4)": 0, "(2, 5)": 1, "(2, 6)": 0, "(2, 7)": 0, "(2, 8)": 1, "(2, 9)": 0, "(2, 10)": 0, "(3, 4)": 1, "(3, 5)": 0, "(3, 6)": 0, "(3, 7)": 1, "(3, 8)": 1, "(3, 9)": 0, "(3, 10)": 0, "(4, 5)": 1, "(4, 6)": 0, "(4, 7)": 1, "(4, 8)": 0, "(4, 9)": 0, "(4, 10)": 0, "(5, 6)": 1, "(5, 7)": 0, "(5, 8)": 0, "(5, 9)": 0, "(5, 10)": 1, "(6, 7)": 0, "(6, 8)": 1, "(6, 9)": 1, "(6, 10)": 1, "(7, 8)": 0, "(7, 9)": 0, "(7, 10)": 0, "(8, 9)": 1, "(8, 10)": 0, "(9, 10)": 1}, "phi": {"(1, 2, 1)": 922, "(1, 2, 2)": 811, "(1, 2, 3)": 611, "(1, 2, 4)": 307, "(1, 2, 5)": 223, "(1, 2, 6)": 432, "(1, 2, 7)": 486, "(1, 2, 8)": 849, "(1, 2, 9)": 469, "(1, 2, 10)": 664, "(1, 3, 1)": 77, "(1, 3, 2)": 771, "(1, 3, 3)": 685, "(1, 3, 4)": 648, "(1, 3, 5)": 290, "(1, 3, 6)": 332, "(1, 3, 7)": 561, "(1, 3, 8)": 834, "(1, 3, 9)": 998, "(1, 3, 10)": 241, "(1, 4, 1)": 827, "(1, 4, 2)": 163, "(1, 4, 3)": 493, "(1, 4, 4)": 411, "(1, 4, 5)": 507, "(1, 4, 6)": 221, "(1, 4, 7)": 463, "(1, 4, 8)": 860, "(1, 4, 9)": 853, "(1, 4, 10)": 29, "(1, 5, 1)": 691, "(1, 5, 2)": 733, "(1, 5, 3)": 986, "(1, 5, 4)": 172, "(1, 5, 5)": 209, "(1, 5, 6)": 646, "(1, 5, 7)": 132, "(1, 5, 8)": 410, "(1, 5, 9)": 92, "(1, 5, 10)": 173, "(1, 6, 1)": 177, "(1, 6, 2)": 367, "(1, 6, 3)": 650, "(1, 6, 4)": 825, "(1, 6, 5)": 31, "(1, 6, 6)": 431, "(1, 6, 7)": 691, "(1, 6, 8)": 771, "(1, 6, 9)": 585, "(1, 6, 10)": 777, "(1, 7, 1)": 362, "(1, 7, 2)": 914, "(1, 7, 3)": 306, "(1, 7, 4)": 573, "(1, 7, 5)": 51, "(1, 7, 6)": 649, "(1, 7, 7)": 387, "(1, 7, 8)": 313, "(1, 7, 9)": 320, "(1, 7, 10)": 366, "(1, 8, 1)": 236, "(1, 8, 2)": 438, "(1, 8, 3)": 500, "(1, 8, 4)": 287, "(1, 8, 5)": 169, "(1, 8, 6)": 617, "(1, 8, 7)": 118, "(1, 8, 8)": 131, "(1, 8, 9)": 961, "(1, 8, 10)": 440, "(1, 9, 1)": 179, "(1, 9, 2)": 770, "(1, 9, 3)": 252, "(1, 9, 4)": 256, "(1, 9, 5)": 397, "(1, 9, 6)": 90, "(1, 9, 7)": 995, "(1, 9, 8)": 7, "(1, 9, 9)": 431, "(1, 9, 10)": 773, "(1, 10, 1)": 249, "(1, 10, 2)": 377, "(1, 10, 3)": 356, "(1, 10, 4)": 282, "(1, 10, 5)": 957, "(1, 10, 6)": 37, "(1, 10, 7)": 913, "(1, 10, 8)": 8, "(1, 10, 9)": 391, "(1, 10, 10)": 9, "(2, 1, 1)": 53, "(2, 1, 2)": 673, "(2, 1, 3)": 351, "(2, 1, 4)": 389, "(2, 1, 5)": 916, "(2, 1, 6)": 732, "(2, 1, 7)": 431, "(2, 1, 8)": 41, "(2, 1, 9)": 750, "(2, 1, 10)": 61, "(2, 3, 1)": 357, "(2, 3, 2)": 751, "(2, 3, 3)": 51, "(2, 3, 4)": 538, "(2, 3, 5)": 939, "(2, 3, 6)": 274, "(2, 3, 7)": 461, "(2, 3, 8)": 66, "(2, 3, 9)": 362, "(2, 3, 10)": 653, "(2, 4, 1)": 710, "(2, 4, 2)": 30, "(2, 4, 3)": 72, "(2, 4, 4)": 63, "(2, 4, 5)": 527, "(2, 4, 6)": 867, "(2, 4, 7)": 61, "(2, 4, 8)": 28, "(2, 4, 9)": 813, "(2, 4, 10)": 913, "(2, 5, 1)": 556, "(2, 5, 2)": 121, "(2, 5, 3)": 590, "(2, 5, 4)": 77, "(2, 5, 5)": 808, "(2, 5, 6)": 595, "(2, 5, 7)": 851, "(2, 5, 8)": 702, "(2, 5, 9)": 480, "(2, 5, 10)": 211, "(2, 6, 1)": 893, "(2, 6, 2)": 960, "(2, 6, 3)": 483, "(2, 6, 4)": 452, "(2, 6, 5)": 574, "(2, 6, 6)": 908, "(2, 6, 7)": 331, "(2, 6, 8)": 213, "(2, 6, 9)": 718, "(2, 6, 10)": 58, "(2, 7, 1)": 299, "(2, 7, 2)": 671, "(2, 7, 3)": 586, "(2, 7, 4)": 236, "(2, 7, 5)": 478, "(2, 7, 6)": 181, "(2, 7, 7)": 376, "(2, 7, 8)": 294, "(2, 7, 9)": 983, "(2, 7, 10)": 664, "(2, 8, 1)": 574, "(2, 8, 2)": 187, "(2, 8, 3)": 639, "(2, 8, 4)": 243, "(2, 8, 5)": 37, "(2, 8, 6)": 605, "(2, 8, 7)": 249, "(2, 8, 8)": 493, "(2, 8, 9)": 3, "(2, 8, 10)": 456, "(2, 9, 1)": 54, "(2, 9, 2)": 937, "(2, 9, 3)": 533, "(2, 9, 4)": 416, "(2, 9, 5)": 427, "(2, 9, 6)": 839, "(2, 9, 7)": 490, "(2, 9, 8)": 937, "(2, 9, 9)": 87, "(2, 9, 10)": 63, "(2, 10, 1)": 898, "(2, 10, 2)": 19, "(2, 10, 3)": 871, "(2, 10, 4)": 660, "(2, 10, 5)": 146, "(2, 10, 6)": 745, "(2, 10, 7)": 382, "(2, 10, 8)": 910, "(2, 10, 9)": 258, "(2, 10, 10)": 105, "(3, 1, 1)": 771, "(3, 1, 2)": 779, "(3, 1, 3)": 860, "(3, 1, 4)": 549, "(3, 1, 5)": 741, "(3, 1, 6)": 63, "(3, 1, 7)": 528, "(3, 1, 8)": 371, "(3, 1, 9)": 136, "(3, 1, 10)": 912, "(3, 2, 1)": 756, "(3, 2, 2)": 128, "(3, 2, 3)": 197, "(3, 2, 4)": 676, "(3, 2, 5)": 230, "(3, 2, 6)": 803, "(3, 2, 7)": 367, "(3, 2, 8)": 522, "(3, 2, 9)": 46, "(3, 2, 10)": 35, "(3, 4, 1)": 950, "(3, 4, 2)": 563, "(3, 4, 3)": 164, "(3, 4, 4)": 73, "(3, 4, 5)": 905, "(3, 4, 6)": 41, "(3, 4, 7)": 289, "(3, 4, 8)": 954, "(3, 4, 9)": 120, "(3, 4, 10)": 440, "(3, 5, 1)": 94, "(3, 5, 2)": 852, "(3, 5, 3)": 365, "(3, 5, 4)": 318, "(3, 5, 5)": 544, "(3, 5, 6)": 646, "(3, 5, 7)": 787, "(3, 5, 8)": 963, "(3, 5, 9)": 876, "(3, 5, 10)": 901, "(3, 6, 1)": 133, "(3, 6, 2)": 105, "(3, 6, 3)": 923, "(3, 6, 4)": 671, "(3, 6, 5)": 725, "(3, 6, 6)": 669, "(3, 6, 7)": 814, "(3, 6, 8)": 148, "(3, 6, 9)": 193, "(3, 6, 10)": 988, "(3, 7, 1)": 293, "(3, 7, 2)": 990, "(3, 7, 3)": 181, "(3, 7, 4)": 381, "(3, 7, 5)": 850, "(3, 7, 6)": 924, "(3, 7, 7)": 658, "(3, 7, 8)": 724, "(3, 7, 9)": 503, "(3, 7, 10)": 952, "(3, 8, 1)": 797, "(3, 8, 2)": 460, "(3, 8, 3)": 70, "(3, 8, 4)": 128, "(3, 8, 5)": 129, "(3, 8, 6)": 846, "(3, 8, 7)": 423, "(3, 8, 8)": 442, "(3, 8, 9)": 149, "(3, 8, 10)": 774, "(3, 9, 1)": 892, "(3, 9, 2)": 341, "(3, 9, 3)": 495, "(3, 9, 4)": 942, "(3, 9, 5)": 814, "(3, 9, 6)": 660, "(3, 9, 7)": 631, "(3, 9, 8)": 416, "(3, 9, 9)": 127, "(3, 9, 10)": 144, "(3, 10, 1)": 366, "(3, 10, 2)": 133, "(3, 10, 3)": 187, "(3, 10, 4)": 298, "(3, 10, 5)": 761, "(3, 10, 6)": 897, "(3, 10, 7)": 524, "(3, 10, 8)": 24, "(3, 10, 9)": 918, "(3, 10, 10)": 361, "(4, 1, 1)": 51, "(4, 1, 2)": 607, "(4, 1, 3)": 189, "(4, 1, 4)": 292, "(4, 1, 5)": 653, "(4, 1, 6)": 273, "(4, 1, 7)": 959, "(4, 1, 8)": 58, "(4, 1, 9)": 933, "(4, 1, 10)": 706, "(4, 2, 1)": 500, "(4, 2, 2)": 972, "(4, 2, 3)": 728, "(4, 2, 4)": 670, "(4, 2, 5)": 202, "(4, 2, 6)": 110, "(4, 2, 7)": 782, "(4, 2, 8)": 472, "(4, 2, 9)": 585, "(4, 2, 10)": 982, "(4, 3, 1)": 179, "(4, 3, 2)": 36, "(4, 3, 3)": 632, "(4, 3, 4)": 216, "(4, 3, 5)": 531, "(4, 3, 6)": 424, "(4, 3, 7)": 288, "(4, 3, 8)": 614, "(4, 3, 9)": 694, "(4, 3, 10)": 935, "(4, 5, 1)": 815, "(4, 5, 2)": 839, "(4, 5, 3)": 970, "(4, 5, 4)": 393, "(4, 5, 5)": 868, "(4, 5, 6)": 270, "(4, 5, 7)": 819, "(4, 5, 8)": 924, "(4, 5, 9)": 73, "(4, 5, 10)": 769, "(4, 6, 1)": 471, "(4, 6, 2)": 48, "(4, 6, 3)": 683, "(4, 6, 4)": 523, "(4, 6, 5)": 295, "(4, 6, 6)": 913, "(4, 6, 7)": 43, "(4, 6, 8)": 973, "(4, 6, 9)": 426, "(4, 6, 10)": 253, "(4, 7, 1)": 926, "(4, 7, 2)": 380, "(4, 7, 3)": 205, "(4, 7, 4)": 873, "(4, 7, 5)": 693, "(4, 7, 6)": 207, "(4, 7, 7)": 552, "(4, 7, 8)": 641, "(4, 7, 9)": 568, "(4, 7, 10)": 259, "(4, 8, 1)": 63, "(4, 8, 2)": 675, "(4, 8, 3)": 510, "(4, 8, 4)": 962, "(4, 8, 5)": 75, "(4, 8, 6)": 471, "(4, 8, 7)": 468, "(4, 8, 8)": 474, "(4, 8, 9)": 410, "(4, 8, 10)": 791, "(4, 9, 1)": 581, "(4, 9, 2)": 408, "(4, 9, 3)": 320, "(4, 9, 4)": 476, "(4, 9, 5)": 978, "(4, 9, 6)": 638, "(4, 9, 7)": 12, "(4, 9, 8)": 987, "(4, 9, 9)": 219, "(4, 9, 10)": 643, "(4, 10, 1)": 502, "(4, 10, 2)": 682, "(4, 10, 3)": 488, "(4, 10, 4)": 503, "(4, 10, 5)": 325, "(4, 10, 6)": 555, "(4, 10, 7)": 1000, "(4, 10, 8)": 350, "(4, 10, 9)": 570, "(4, 10, 10)": 779, "(5, 1, 1)": 594, "(5, 1, 2)": 640, "(5, 1, 3)": 423, "(5, 1, 4)": 827, "(5, 1, 5)": 851, "(5, 1, 6)": 722, "(5, 1, 7)": 655, "(5, 1, 8)": 763, "(5, 1, 9)": 626, "(5, 1, 10)": 254, "(5, 2, 1)": 818, "(5, 2, 2)": 455, "(5, 2, 3)": 794, "(5, 2, 4)": 436, "(5, 2, 5)": 513, "(5, 2, 6)": 520, "(5, 2, 7)": 246, "(5, 2, 8)": 3, "(5, 2, 9)": 121, "(5, 2, 10)": 430, "(5, 3, 1)": 480, "(5, 3, 2)": 206, "(5, 3, 3)": 859, "(5, 3, 4)": 439, "(5, 3, 5)": 28, "(5, 3, 6)": 295, "(5, 3, 7)": 707, "(5, 3, 8)": 106, "(5, 3, 9)": 243, "(5, 3, 10)": 541, "(5, 4, 1)": 975, "(5, 4, 2)": 965, "(5, 4, 3)": 870, "(5, 4, 4)": 972, "(5, 4, 5)": 737, "(5, 4, 6)": 236, "(5, 4, 7)": 261, "(5, 4, 8)": 89, "(5, 4, 9)": 331, "(5, 4, 10)": 808, "(5, 6, 1)": 389, "(5, 6, 2)": 164, "(5, 6, 3)": 702, "(5, 6, 4)": 465, "(5, 6, 5)": 101, "(5, 6, 6)": 717, "(5, 6, 7)": 136, "(5, 6, 8)": 515, "(5, 6, 9)": 293, "(5, 6, 10)": 197, "(5, 7, 1)": 177, "(5, 7, 2)": 425, "(5, 7, 3)": 393, "(5, 7, 4)": 541, "(5, 7, 5)": 278, "(5, 7, 6)": 862, "(5, 7, 7)": 412, "(5, 7, 8)": 559, "(5, 7, 9)": 309, "(5, 7, 10)": 403, "(5, 8, 1)": 261, "(5, 8, 2)": 978, "(5, 8, 3)": 78, "(5, 8, 4)": 488, "(5, 8, 5)": 271, "(5, 8, 6)": 805, "(5, 8, 7)": 919, "(5, 8, 8)": 426, "(5, 8, 9)": 589, "(5, 8, 10)": 106, "(5, 9, 1)": 882, "(5, 9, 2)": 461, "(5, 9, 3)": 352, "(5, 9, 4)": 846, "(5, 9, 5)": 102, "(5, 9, 6)": 960, "(5, 9, 7)": 818, "(5, 9, 8)": 782, "(5, 9, 9)": 104, "(5, 9, 10)": 980, "(5, 10, 1)": 558, "(5, 10, 2)": 384, "(5, 10, 3)": 501, "(5, 10, 4)": 247, "(5, 10, 5)": 6, "(5, 10, 6)": 538, "(5, 10, 7)": 636, "(5, 10, 8)": 948, "(5, 10, 9)": 168, "(5, 10, 10)": 869, "(6, 1, 1)": 700, "(6, 1, 2)": 81, "(6, 1, 3)": 858, "(6, 1, 4)": 904, "(6, 1, 5)": 201, "(6, 1, 6)": 396, "(6, 1, 7)": 640, "(6, 1, 8)": 218, "(6, 1, 9)": 724, "(6, 1, 10)": 19, "(6, 2, 1)": 514, "(6, 2, 2)": 960, "(6, 2, 3)": 460, "(6, 2, 4)": 117, "(6, 2, 5)": 992, "(6, 2, 6)": 603, "(6, 2, 7)": 661, "(6, 2, 8)": 288, "(6, 2, 9)": 873, "(6, 2, 10)": 812, "(6, 3, 1)": 83, "(6, 3, 2)": 692, "(6, 3, 3)": 505, "(6, 3, 4)": 765, "(6, 3, 5)": 66, "(6, 3, 6)": 484, "(6, 3, 7)": 523, "(6, 3, 8)": 468, "(6, 3, 9)": 19, "(6, 3, 10)": 40, "(6, 4, 1)": 802, "(6, 4, 2)": 811, "(6, 4, 3)": 772, "(6, 4, 4)": 930, "(6, 4, 5)": 417, "(6, 4, 6)": 580, "(6, 4, 7)": 155, "(6, 4, 8)": 373, "(6, 4, 9)": 136, "(6, 4, 10)": 357, "(6, 5, 1)": 780, "(6, 5, 2)": 306, "(6, 5, 3)": 958, "(6, 5, 4)": 158, "(6, 5, 5)": 495, "(6, 5, 6)": 257, "(6, 5, 7)": 385, "(6, 5, 8)": 254, "(6, 5, 9)": 756, "(6, 5, 10)": 501, "(6, 7, 1)": 912, "(6, 7, 2)": 301, "(6, 7, 3)": 806, "(6, 7, 4)": 838, "(6, 7, 5)": 653, "(6, 7, 6)": 818, "(6, 7, 7)": 117, "(6, 7, 8)": 959, "(6, 7, 9)": 757, "(6, 7, 10)": 33, "(6, 8, 1)": 384, "(6, 8, 2)": 816, "(6, 8, 3)": 583, "(6, 8, 4)": 475, "(6, 8, 5)": 862, "(6, 8, 6)": 345, "(6, 8, 7)": 233, "(6, 8, 8)": 1, "(6, 8, 9)": 86, "(6, 8, 10)": 646, "(6, 9, 1)": 778, "(6, 9, 2)": 589, "(6, 9, 3)": 812, "(6, 9, 4)": 247, "(6, 9, 5)": 221, "(6, 9, 6)": 22, "(6, 9, 7)": 562, "(6, 9, 8)": 502, "(6, 9, 9)": 576, "(6, 9, 10)": 393, "(6, 10, 1)": 285, "(6, 10, 2)": 939, "(6, 10, 3)": 124, "(6, 10, 4)": 802, "(6, 10, 5)": 135, "(6, 10, 6)": 235, "(6, 10, 7)": 294, "(6, 10, 8)": 630, "(6, 10, 9)": 339, "(6, 10, 10)": 718, "(7, 1, 1)": 595, "(7, 1, 2)": 325, "(7, 1, 3)": 919, "(7, 1, 4)": 881, "(7, 1, 5)": 788, "(7, 1, 6)": 324, "(7, 1, 7)": 502, "(7, 1, 8)": 33, "(7, 1, 9)": 359, "(7, 1, 10)": 608, "(7, 2, 1)": 639, "(7, 2, 2)": 615, "(7, 2, 3)": 678, "(7, 2, 4)": 386, "(7, 2, 5)": 710, "(7, 2, 6)": 559, "(7, 2, 7)": 808, "(7, 2, 8)": 366, "(7, 2, 9)": 187, "(7, 2, 10)": 804, "(7, 3, 1)": 314, "(7, 3, 2)": 6, "(7, 3, 3)": 941, "(7, 3, 4)": 449, "(7, 3, 5)": 560, "(7, 3, 6)": 422, "(7, 3, 7)": 898, "(7, 3, 8)": 294, "(7, 3, 9)": 630, "(7, 3, 10)": 765, "(7, 4, 1)": 994, "(7, 4, 2)": 562, "(7, 4, 3)": 377, "(7, 4, 4)": 198, "(7, 4, 5)": 659, "(7, 4, 6)": 940, "(7, 4, 7)": 420, "(7, 4, 8)": 480, "(7, 4, 9)": 884, "(7, 4, 10)": 475, "(7, 5, 1)": 557, "(7, 5, 2)": 736, "(7, 5, 3)": 243, "(7, 5, 4)": 538, "(7, 5, 5)": 176, "(7, 5, 6)": 404, "(7, 5, 7)": 364, "(7, 5, 8)": 188, "(7, 5, 9)": 379, "(7, 5, 10)": 396, "(7, 6, 1)": 559, "(7, 6, 2)": 878, "(7, 6, 3)": 864, "(7, 6, 4)": 543, "(7, 6, 5)": 869, "(7, 6, 6)": 698, "(7, 6, 7)": 430, "(7, 6, 8)": 829, "(7, 6, 9)": 854, "(7, 6, 10)": 768, "(7, 8, 1)": 489, "(7, 8, 2)": 205, "(7, 8, 3)": 310, "(7, 8, 4)": 444, "(7, 8, 5)": 397, "(7, 8, 6)": 667, "(7, 8, 7)": 6, "(7, 8, 8)": 247, "(7, 8, 9)": 657, "(7, 8, 10)": 561, "(7, 9, 1)": 485, "(7, 9, 2)": 773, "(7, 9, 3)": 46, "(7, 9, 4)": 773, "(7, 9, 5)": 642, "(7, 9, 6)": 879, "(7, 9, 7)": 446, "(7, 9, 8)": 422, "(7, 9, 9)": 4, "(7, 9, 10)": 87, "(7, 10, 1)": 886, "(7, 10, 2)": 873, "(7, 10, 3)": 415, "(7, 10, 4)": 902, "(7, 10, 5)": 904, "(7, 10, 6)": 525, "(7, 10, 7)": 495, "(7, 10, 8)": 44, "(7, 10, 9)": 747, "(7, 10, 10)": 257, "(8, 1, 1)": 388, "(8, 1, 2)": 274, "(8, 1, 3)": 910, "(8, 1, 4)": 244, "(8, 1, 5)": 549, "(8, 1, 6)": 560, "(8, 1, 7)": 380, "(8, 1, 8)": 793, "(8, 1, 9)": 278, "(8, 1, 10)": 853, "(8, 2, 1)": 345, "(8, 2, 2)": 207, "(8, 2, 3)": 746, "(8, 2, 4)": 809, "(8, 2, 5)": 882, "(8, 2, 6)": 217, "(8, 2, 7)": 135, "(8, 2, 8)": 723, "(8, 2, 9)": 601, "(8, 2, 10)": 186, "(8, 3, 1)": 803, "(8, 3, 2)": 469, "(8, 3, 3)": 617, "(8, 3, 4)": 808, "(8, 3, 5)": 684, "(8, 3, 6)": 908, "(8, 3, 7)": 306, "(8, 3, 8)": 986, "(8, 3, 9)": 1000, "(8, 3, 10)": 397, "(8, 4, 1)": 868, "(8, 4, 2)": 860, "(8, 4, 3)": 211, "(8, 4, 4)": 796, "(8, 4, 5)": 140, "(8, 4, 6)": 906, "(8, 4, 7)": 238, "(8, 4, 8)": 158, "(8, 4, 9)": 546, "(8, 4, 10)": 675, "(8, 5, 1)": 506, "(8, 5, 2)": 764, "(8, 5, 3)": 344, "(8, 5, 4)": 812, "(8, 5, 5)": 542, "(8, 5, 6)": 695, "(8, 5, 7)": 175, "(8, 5, 8)": 831, "(8, 5, 9)": 275, "(8, 5, 10)": 746, "(8, 6, 1)": 57, "(8, 6, 2)": 300, "(8, 6, 3)": 415, "(8, 6, 4)": 612, "(8, 6, 5)": 743, "(8, 6, 6)": 141, "(8, 6, 7)": 256, "(8, 6, 8)": 531, "(8, 6, 9)": 7, "(8, 6, 10)": 915, "(8, 7, 1)": 958, "(8, 7, 2)": 136, "(8, 7, 3)": 57, "(8, 7, 4)": 882, "(8, 7, 5)": 19, "(8, 7, 6)": 275, "(8, 7, 7)": 151, "(8, 7, 8)": 826, "(8, 7, 9)": 876, "(8, 7, 10)": 717, "(8, 9, 1)": 760, "(8, 9, 2)": 496, "(8, 9, 3)": 806, "(8, 9, 4)": 266, "(8, 9, 5)": 322, "(8, 9, 6)": 83, "(8, 9, 7)": 159, "(8, 9, 8)": 677, "(8, 9, 9)": 593, "(8, 9, 10)": 915, "(8, 10, 1)": 649, "(8, 10, 2)": 706, "(8, 10, 3)": 415, "(8, 10, 4)": 47, "(8, 10, 5)": 256, "(8, 10, 6)": 279, "(8, 10, 7)": 892, "(8, 10, 8)": 911, "(8, 10, 9)": 462, "(8, 10, 10)": 533, "(9, 1, 1)": 937, "(9, 1, 2)": 31, "(9, 1, 3)": 268, "(9, 1, 4)": 343, "(9, 1, 5)": 916, "(9, 1, 6)": 809, "(9, 1, 7)": 295, "(9, 1, 8)": 346, "(9, 1, 9)": 530, "(9, 1, 10)": 513, "(9, 2, 1)": 159, "(9, 2, 2)": 29, "(9, 2, 3)": 57, "(9, 2, 4)": 722, "(9, 2, 5)": 626, "(9, 2, 6)": 195, "(9, 2, 7)": 11, "(9, 2, 8)": 673, "(9, 2, 9)": 107, "(9, 2, 10)": 476, "(9, 3, 1)": 595, "(9, 3, 2)": 663, "(9, 3, 3)": 609, "(9, 3, 4)": 358, "(9, 3, 5)": 434, "(9, 3, 6)": 532, "(9, 3, 7)": 410, "(9, 3, 8)": 369, "(9, 3, 9)": 664, "(9, 3, 10)": 550, "(9, 4, 1)": 554, "(9, 4, 2)": 420, "(9, 4, 3)": 540, "(9, 4, 4)": 985, "(9, 4, 5)": 2, "(9, 4, 6)": 658, "(9, 4, 7)": 686, "(9, 4, 8)": 567, "(9, 4, 9)": 914, "(9, 4, 10)": 593, "(9, 5, 1)": 838, "(9, 5, 2)": 225, "(9, 5, 3)": 662, "(9, 5, 4)": 346, "(9, 5, 5)": 52, "(9, 5, 6)": 955, "(9, 5, 7)": 962, "(9, 5, 8)": 1, "(9, 5, 9)": 925, "(9, 5, 10)": 547, "(9, 6, 1)": 384, "(9, 6, 2)": 587, "(9, 6, 3)": 831, "(9, 6, 4)": 686, "(9, 6, 5)": 741, "(9, 6, 6)": 907, "(9, 6, 7)": 713, "(9, 6, 8)": 836, "(9, 6, 9)": 13, "(9, 6, 10)": 205, "(9, 7, 1)": 137, "(9, 7, 2)": 237, "(9, 7, 3)": 365, "(9, 7, 4)": 537, "(9, 7, 5)": 830, "(9, 7, 6)": 948, "(9, 7, 7)": 504, "(9, 7, 8)": 586, "(9, 7, 9)": 839, "(9, 7, 10)": 715, "(9, 8, 1)": 41, "(9, 8, 2)": 647, "(9, 8, 3)": 676, "(9, 8, 4)": 985, "(9, 8, 5)": 804, "(9, 8, 6)": 497, "(9, 8, 7)": 842, "(9, 8, 8)": 557, "(9, 8, 9)": 219, "(9, 8, 10)": 912, "(9, 10, 1)": 422, "(9, 10, 2)": 265, "(9, 10, 3)": 964, "(9, 10, 4)": 797, "(9, 10, 5)": 276, "(9, 10, 6)": 774, "(9, 10, 7)": 905, "(9, 10, 8)": 715, "(9, 10, 9)": 959, "(9, 10, 10)": 794, "(10, 1, 1)": 296, "(10, 1, 2)": 473, "(10, 1, 3)": 867, "(10, 1, 4)": 133, "(10, 1, 5)": 69, "(10, 1, 6)": 16, "(10, 1, 7)": 546, "(10, 1, 8)": 971, "(10, 1, 9)": 671, "(10, 1, 10)": 45, "(10, 2, 1)": 64, "(10, 2, 2)": 404, "(10, 2, 3)": 369, "(10, 2, 4)": 330, "(10, 2, 5)": 970, "(10, 2, 6)": 14, "(10, 2, 7)": 575, "(10, 2, 8)": 50, "(10, 2, 9)": 77, "(10, 2, 10)": 87, "(10, 3, 1)": 215, "(10, 3, 2)": 994, "(10, 3, 3)": 706, "(10, 3, 4)": 73, "(10, 3, 5)": 0, "(10, 3, 6)": 320, "(10, 3, 7)": 267, "(10, 3, 8)": 990, "(10, 3, 9)": 259, "(10, 3, 10)": 473, "(10, 4, 1)": 823, "(10, 4, 2)": 787, "(10, 4, 3)": 821, "(10, 4, 4)": 233, "(10, 4, 5)": 806, "(10, 4, 6)": 479, "(10, 4, 7)": 992, "(10, 4, 8)": 512, "(10, 4, 9)": 309, "(10, 4, 10)": 115, "(10, 5, 1)": 855, "(10, 5, 2)": 938, "(10, 5, 3)": 213, "(10, 5, 4)": 266, "(10, 5, 5)": 712, "(10, 5, 6)": 328, "(10, 5, 7)": 43, "(10, 5, 8)": 273, "(10, 5, 9)": 491, "(10, 5, 10)": 619, "(10, 6, 1)": 561, "(10, 6, 2)": 937, "(10, 6, 3)": 765, "(10, 6, 4)": 70, "(10, 6, 5)": 818, "(10, 6, 6)": 212, "(10, 6, 7)": 639, "(10, 6, 8)": 267, "(10, 6, 9)": 986, "(10, 6, 10)": 987, "(10, 7, 1)": 248, "(10, 7, 2)": 419, "(10, 7, 3)": 85, "(10, 7, 4)": 183, "(10, 7, 5)": 186, "(10, 7, 6)": 119, "(10, 7, 7)": 96, "(10, 7, 8)": 626, "(10, 7, 9)": 907, "(10, 7, 10)": 895, "(10, 8, 1)": 268, "(10, 8, 2)": 363, "(10, 8, 3)": 256, "(10, 8, 4)": 741, "(10, 8, 5)": 737, "(10, 8, 6)": 718, "(10, 8, 7)": 632, "(10, 8, 8)": 101, "(10, 8, 9)": 89, "(10, 8, 10)": 301, "(10, 9, 1)": 520, "(10, 9, 2)": 972, "(10, 9, 3)": 341, "(10, 9, 4)": 196, "(10, 9, 5)": 595, "(10, 9, 6)": 66, "(10, 9, 7)": 589, "(10, 9, 8)": 236, "(10, 9, 9)": 524, "(10, 9, 10)": 840}, "beta": {"(1, 2, 1)": 0.5351400823798586, "(1, 2, 2)": 0.8438099729128327, "(1, 2, 3)": 0.6792951403934399, "(1, 2, 4)": 0.3963454637665098, "(1, 2, 5)": 0.6289250567340203, "(1, 2, 6)": 0.5233563589037538, "(1, 2, 7)": 0.4584306015700801, "(1, 2, 8)": 0.2731847675777902, "(1, 2, 9)": 0.5411308808278855, "(1, 2, 10)": 0.13433226327341644, "(1, 3, 1)": 0.43500922507074546, "(1, 3, 2)": 0.7462117816982727, "(1, 3, 3)": 0.5189855853129587, "(1, 3, 4)": 0.47513991822964285, "(1, 3, 5)": 0.24616420270459338, "(1, 3, 6)": 0.8011926119057731, "(1, 3, 7)": 0.7217713126937082, "(1, 3, 8)": 0.6576819281913456, "(1, 3, 9)": 0.11411149191044663, "(1, 3, 10)": 0.7211674863270482, "(1, 4, 1)": 0.32549008967949944, "(1, 4, 2)": 0.5151815379293961, "(1, 4, 3)": 0.19747147936904128, "(1, 4, 4)": 0.5988084102741484, "(1, 4, 5)": 0.2705064315156045, "(1, 4, 6)": 0.8868888379330198, "(1, 4, 7)": 0.3407593154330626, "(1, 4, 8)": 0.6865331603746802, "(1, 4, 9)": 0.4168877088157571, "(1, 4, 10)": 0.5945321516738064, "(1, 5, 1)": 0.12319857772384823, "(1, 5, 2)": 0.1268252634310903, "(1, 5, 3)": 0.13015434303061815, "(1, 5, 4)": 0.761946550289745, "(1, 5, 5)": 0.5797336310721731, "(1, 5, 6)": 0.8878224739548443, "(1, 5, 7)": 0.45773958522592395, "(1, 5, 8)": 0.30799073655309406, "(1, 5, 9)": 0.3829927857324703, "(1, 5, 10)": 0.4544759693541266, "(1, 6, 1)": 0.4932815037292704, "(1, 6, 2)": 0.3413340644857373, "(1, 6, 3)": 0.665003503853532, "(1, 6, 4)": 0.5650624341884731, "(1, 6, 5)": 0.38625977304706827, "(1, 6, 6)": 0.4564624882819862, "(1, 6, 7)": 0.783196211431637, "(1, 6, 8)": 0.8559363065821896, "(1, 6, 9)": 0.8600102788008578, "(1, 6, 10)": 0.3027260904156098, "(1, 7, 1)": 0.7921473759277396, "(1, 7, 2)": 0.295494294060073, "(1, 7, 3)": 0.350259567960701, "(1, 7, 4)": 0.16620642670036362, "(1, 7, 5)": 0.6923521783940576, "(1, 7, 6)": 0.5750999090706677, "(1, 7, 7)": 0.4194141076616368, "(1, 7, 8)": 0.22629119264112144, "(1, 7, 9)": 0.7557416099528558, "(1, 7, 10)": 0.13102437156485378, "(1, 8, 1)": 0.7755853465049846, "(1, 8, 2)": 0.22651289529663618, "(1, 8, 3)": 0.5409734667168306, "(1, 8, 4)": 0.3972342860263892, "(1, 8, 5)": 0.3652453248519094, "(1, 8, 6)": 0.5261294936993423, "(1, 8, 7)": 0.6880560520508572, "(1, 8, 8)": 0.10669704513508221, "(1, 8, 9)": 0.21164315962072458, "(1, 8, 10)": 0.46109342758098326, "(1, 9, 1)": 0.865892765111416, "(1, 9, 2)": 0.721655719496466, "(1, 9, 3)": 0.4194547437605688, "(1, 9, 4)": 0.6609316648571358, "(1, 9, 5)": 0.13757729074040964, "(1, 9, 6)": 0.6167430664970663, "(1, 9, 7)": 0.14106499467654432, "(1, 9, 8)": 0.6085314604270248, "(1, 9, 9)": 0.5051555917400155, "(1, 9, 10)": 0.23050863815975192, "(1, 10, 1)": 0.45278653653694945, "(1, 10, 2)": 0.3911273579523823, "(1, 10, 3)": 0.873575741265282, "(1, 10, 4)": 0.5483273804179494, "(1, 10, 5)": 0.6613610679602787, "(1, 10, 6)": 0.4855183025209453, "(1, 10, 7)": 0.49855552194859987, "(1, 10, 8)": 0.18924699560186822, "(1, 10, 9)": 0.5424213825622113, "(1, 10, 10)": 0.5687023847870181, "(2, 1, 1)": 0.1535007964837762, "(2, 1, 2)": 0.10964228171700006, "(2, 1, 3)": 0.4536504470669307, "(2, 1, 4)": 0.45887315009069596, "(2, 1, 5)": 0.8236005285753147, "(2, 1, 6)": 0.38621524735592816, "(2, 1, 7)": 0.13925808786906135, "(2, 1, 8)": 0.35466723955483415, "(2, 1, 9)": 0.865552817613746, "(2, 1, 10)": 0.5169881588956405, "(2, 3, 1)": 0.6539911718393793, "(2, 3, 2)": 0.569235578213887, "(2, 3, 3)": 0.7888635698309696, "(2, 3, 4)": 0.6781125620537443, "(2, 3, 5)": 0.28405298582881133, "(2, 3, 6)": 0.7873583217830169, "(2, 3, 7)": 0.49403459178908526, "(2, 3, 8)": 0.5448361264640107, "(2, 3, 9)": 0.14073297437884574, "(2, 3, 10)": 0.398085444948449, "(2, 4, 1)": 0.5609191460862929, "(2, 4, 2)": 0.859586785865768, "(2, 4, 3)": 0.7661339941259956, "(2, 4, 4)": 0.6237714069059644, "(2, 4, 5)": 0.13213645933385704, "(2, 4, 6)": 0.805563183791098, "(2, 4, 7)": 0.5039416885103324, "(2, 4, 8)": 0.7395601411223861, "(2, 4, 9)": 0.2744749266547104, "(2, 4, 10)": 0.4461471518128973, "(2, 5, 1)": 0.20599956444001438, "(2, 5, 2)": 0.6149869262088276, "(2, 5, 3)": 0.8902987450822641, "(2, 5, 4)": 0.3588472020373662, "(2, 5, 5)": 0.14134588809909135, "(2, 5, 6)": 0.28723266717845064, "(2, 5, 7)": 0.827202821792942, "(2, 5, 8)": 0.12938957283920677, "(2, 5, 9)": 0.2974395657785558, "(2, 5, 10)": 0.639312667940956, "(2, 6, 1)": 0.1773910879874265, "(2, 6, 2)": 0.2404786925509962, "(2, 6, 3)": 0.5390219041566952, "(2, 6, 4)": 0.3171829834758966, "(2, 6, 5)": 0.3577826257755774, "(2, 6, 6)": 0.37043363401685825, "(2, 6, 7)": 0.22810945578962843, "(2, 6, 8)": 0.2449289718916118, "(2, 6, 9)": 0.4169565972150373, "(2, 6, 10)": 0.7334010933674111, "(2, 7, 1)": 0.6322958020606284, "(2, 7, 2)": 0.4270113114124374, "(2, 7, 3)": 0.6655107585187264, "(2, 7, 4)": 0.8992689453601187, "(2, 7, 5)": 0.5516414616062096, "(2, 7, 6)": 0.33701663983924035, "(2, 7, 7)": 0.6362128993401495, "(2, 7, 8)": 0.13129186484489433, "(2, 7, 9)": 0.6928920861871755, "(2, 7, 10)": 0.7000711186915946, "(2, 8, 1)": 0.5614997536669616, "(2, 8, 2)": 0.3711008897301106, "(2, 8, 3)": 0.6699628231770433, "(2, 8, 4)": 0.4433457608833765, "(2, 8, 5)": 0.14846062209890143, "(2, 8, 6)": 0.6905648376971205, "(2, 8, 7)": 0.7356461852956543, "(2, 8, 8)": 0.3585695176434338, "(2, 8, 9)": 0.7712670316858076, "(2, 8, 10)": 0.16556127950985325, "(2, 9, 1)": 0.41629147901777386, "(2, 9, 2)": 0.37409692733232836, "(2, 9, 3)": 0.5556180764367301, "(2, 9, 4)": 0.44119807966131097, "(2, 9, 5)": 0.6474903808338561, "(2, 9, 6)": 0.8078578778021994, "(2, 9, 7)": 0.27697189375260234, "(2, 9, 8)": 0.8940722096092475, "(2, 9, 9)": 0.5221465971742091, "(2, 9, 10)": 0.48673162271436554, "(2, 10, 1)": 0.2961548612843073, "(2, 10, 2)": 0.7887274885431156, "(2, 10, 3)": 0.6195342427889667, "(2, 10, 4)": 0.2070191003724478, "(2, 10, 5)": 0.8663327539997532, "(2, 10, 6)": 0.3460952751142967, "(2, 10, 7)": 0.5915717591285882, "(2, 10, 8)": 0.1308924692330199, "(2, 10, 9)": 0.38709913213333336, "(2, 10, 10)": 0.5655561164150159, "(3, 1, 1)": 0.7176249757568732, "(3, 1, 2)": 0.8783203631025406, "(3, 1, 3)": 0.24858129389876052, "(3, 1, 4)": 0.8722786956935779, "(3, 1, 5)": 0.4703045686286509, "(3, 1, 6)": 0.8978506259507352, "(3, 1, 7)": 0.7454223297694327, "(3, 1, 8)": 0.29293243014428816, "(3, 1, 9)": 0.6056820710862999, "(3, 1, 10)": 0.5897646774315629, "(3, 2, 1)": 0.5814718988046561, "(3, 2, 2)": 0.1813056634728734, "(3, 2, 3)": 0.21017399744775594, "(3, 2, 4)": 0.5017241197281933, "(3, 2, 5)": 0.1175912027334162, "(3, 2, 6)": 0.13917396345612343, "(3, 2, 7)": 0.5738216368375201, "(3, 2, 8)": 0.8470017847378044, "(3, 2, 9)": 0.7546177336591117, "(3, 2, 10)": 0.445700166605432, "(3, 4, 1)": 0.5215620118269934, "(3, 4, 2)": 0.8749411186307022, "(3, 4, 3)": 0.8565542519142464, "(3, 4, 4)": 0.46750900081392366, "(3, 4, 5)": 0.4534055740206373, "(3, 4, 6)": 0.2743840886856364, "(3, 4, 7)": 0.66269880699374, "(3, 4, 8)": 0.8500149197877929, "(3, 4, 9)": 0.5975973242579253, "(3, 4, 10)": 0.2713366547777174, "(3, 5, 1)": 0.8692616514110647, "(3, 5, 2)": 0.8066920075615305, "(3, 5, 3)": 0.3779425122232233, "(3, 5, 4)": 0.7917296491873586, "(3, 5, 5)": 0.7337173998788485, "(3, 5, 6)": 0.8212272003651863, "(3, 5, 7)": 0.15390838304519328, "(3, 5, 8)": 0.25233923996887403, "(3, 5, 9)": 0.5075656084301721, "(3, 5, 10)": 0.5847208119108024, "(3, 6, 1)": 0.27469882703573245, "(3, 6, 2)": 0.2473340502910368, "(3, 6, 3)": 0.4985238216819792, "(3, 6, 4)": 0.529896900971307, "(3, 6, 5)": 0.17086734733917536, "(3, 6, 6)": 0.30699004910453526, "(3, 6, 7)": 0.29265999555384414, "(3, 6, 8)": 0.10472753315765218, "(3, 6, 9)": 0.8247149432139846, "(3, 6, 10)": 0.7997497146449561, "(3, 7, 1)": 0.48146970963042635, "(3, 7, 2)": 0.5122458120363759, "(3, 7, 3)": 0.8967467741609422, "(3, 7, 4)": 0.4319829824039546, "(3, 7, 5)": 0.8143386374984971, "(3, 7, 6)": 0.709295078989107, "(3, 7, 7)": 0.43020751062865226, "(3, 7, 8)": 0.4037163827612513, "(3, 7, 9)": 0.17422604012912207, "(3, 7, 10)": 0.8794239566438691, "(3, 8, 1)": 0.5272463822831058, "(3, 8, 2)": 0.3219662308654645, "(3, 8, 3)": 0.4508158590614545, "(3, 8, 4)": 0.7663571225463586, "(3, 8, 5)": 0.21147728653179093, "(3, 8, 6)": 0.25326883267736544, "(3, 8, 7)": 0.2157927201382176, "(3, 8, 8)": 0.6580809317410883, "(3, 8, 9)": 0.38114095844485707, "(3, 8, 10)": 0.3685872159478678, "(3, 9, 1)": 0.8870942639298462, "(3, 9, 2)": 0.7473323316740926, "(3, 9, 3)": 0.7718029778954438, "(3, 9, 4)": 0.15792176414462783, "(3, 9, 5)": 0.19916151096468016, "(3, 9, 6)": 0.5394670148531516, "(3, 9, 7)": 0.6190289610837216, "(3, 9, 8)": 0.8944068534121636, "(3, 9, 9)": 0.6831173689186729, "(3, 9, 10)": 0.6887613463749246, "(3, 10, 1)": 0.4329323682213305, "(3, 10, 2)": 0.8917444172044822, "(3, 10, 3)": 0.13377631235921195, "(3, 10, 4)": 0.37730164456885407, "(3, 10, 5)": 0.34126237754327776, "(3, 10, 6)": 0.5337686152489486, "(3, 10, 7)": 0.12879057840273536, "(3, 10, 8)": 0.44902856308294103, "(3, 10, 9)": 0.8377957452465659, "(3, 10, 10)": 0.2668290723133949, "(4, 1, 1)": 0.7299306301555966, "(4, 1, 2)": 0.44154814939789155, "(4, 1, 3)": 0.37738505160489444, "(4, 1, 4)": 0.6483728664254533, "(4, 1, 5)": 0.8790883153629856, "(4, 1, 6)": 0.5114280489227165, "(4, 1, 7)": 0.4775536375513115, "(4, 1, 8)": 0.7539532259183391, "(4, 1, 9)": 0.3921783254928942, "(4, 1, 10)": 0.7011825457480925, "(4, 2, 1)": 0.7675755484554979, "(4, 2, 2)": 0.6504836624160656, "(4, 2, 3)": 0.7034863477310566, "(4, 2, 4)": 0.7451499045688607, "(4, 2, 5)": 0.17377654547016047, "(4, 2, 6)": 0.8472290187322892, "(4, 2, 7)": 0.8354673791555, "(4, 2, 8)": 0.47382384238680597, "(4, 2, 9)": 0.16847242538492208, "(4, 2, 10)": 0.8423465566248922, "(4, 3, 1)": 0.23291183153357303, "(4, 3, 2)": 0.8488770456374564, "(4, 3, 3)": 0.5148877113178731, "(4, 3, 4)": 0.7882201701538923, "(4, 3, 5)": 0.42345803914532065, "(4, 3, 6)": 0.6506717862421444, "(4, 3, 7)": 0.3845906262224593, "(4, 3, 8)": 0.15458538254495455, "(4, 3, 9)": 0.33336285243829866, "(4, 3, 10)": 0.787005541023299, "(4, 5, 1)": 0.760416569230134, "(4, 5, 2)": 0.14672051623488774, "(4, 5, 3)": 0.6929888686674386, "(4, 5, 4)": 0.4539609746026806, "(4, 5, 5)": 0.49474274695881204, "(4, 5, 6)": 0.7163451227533479, "(4, 5, 7)": 0.8212632348539846, "(4, 5, 8)": 0.19971021321411442, "(4, 5, 9)": 0.18540986781679383, "(4, 5, 10)": 0.7537930529013893, "(4, 6, 1)": 0.2646359797078752, "(4, 6, 2)": 0.14477964234711316, "(4, 6, 3)": 0.44655038601863895, "(4, 6, 4)": 0.4213561873775561, "(4, 6, 5)": 0.32750598263173575, "(4, 6, 6)": 0.6904364063350965, "(4, 6, 7)": 0.668477109403155, "(4, 6, 8)": 0.4675335944794453, "(4, 6, 9)": 0.3640655685506108, "(4, 6, 10)": 0.8381805400972521, "(4, 7, 1)": 0.42710288247640427, "(4, 7, 2)": 0.4556040285215186, "(4, 7, 3)": 0.8395379939229208, "(4, 7, 4)": 0.8294490931182542, "(4, 7, 5)": 0.36821194857295747, "(4, 7, 6)": 0.5136327002121857, "(4, 7, 7)": 0.631647458093498, "(4, 7, 8)": 0.6837843837633102, "(4, 7, 9)": 0.4442816321032338, "(4, 7, 10)": 0.41502566572206245, "(4, 8, 1)": 0.26966949381084837, "(4, 8, 2)": 0.335728912523934, "(4, 8, 3)": 0.5684006859779941, "(4, 8, 4)": 0.6322059569226648, "(4, 8, 5)": 0.33077372236283253, "(4, 8, 6)": 0.23707387790818846, "(4, 8, 7)": 0.6291627409511048, "(4, 8, 8)": 0.8519457729479294, "(4, 8, 9)": 0.8701409140570452, "(4, 8, 10)": 0.5002825292800097, "(4, 9, 1)": 0.8859939603367136, "(4, 9, 2)": 0.6031388731413669, "(4, 9, 3)": 0.2651861387510114, "(4, 9, 4)": 0.3179180207853436, "(4, 9, 5)": 0.721775994019588, "(4, 9, 6)": 0.8354454341065277, "(4, 9, 7)": 0.5162887722783803, "(4, 9, 8)": 0.5138437465095799, "(4, 9, 9)": 0.4042422515702735, "(4, 9, 10)": 0.7021777622187771, "(4, 10, 1)": 0.5967121023177009, "(4, 10, 2)": 0.7471690612492409, "(4, 10, 3)": 0.1872977089473368, "(4, 10, 4)": 0.2160651528645734, "(4, 10, 5)": 0.6573434492240435, "(4, 10, 6)": 0.8382380885261402, "(4, 10, 7)": 0.5133426511022116, "(4, 10, 8)": 0.32077421644407683, "(4, 10, 9)": 0.23082230600324138, "(4, 10, 10)": 0.7024134436702697, "(5, 1, 1)": 0.14094009011663317, "(5, 1, 2)": 0.592833243940915, "(5, 1, 3)": 0.5049205924263919, "(5, 1, 4)": 0.19551098375003653, "(5, 1, 5)": 0.5094187873666262, "(5, 1, 6)": 0.14433640996663027, "(5, 1, 7)": 0.28857706474650713, "(5, 1, 8)": 0.25412986225041767, "(5, 1, 9)": 0.20835818687664542, "(5, 1, 10)": 0.6185793147928029, "(5, 2, 1)": 0.5583365059734963, "(5, 2, 2)": 0.14958388243253573, "(5, 2, 3)": 0.867459557563074, "(5, 2, 4)": 0.47593260825020645, "(5, 2, 5)": 0.42739223937090653, "(5, 2, 6)": 0.1392396732873297, "(5, 2, 7)": 0.36180133602306785, "(5, 2, 8)": 0.18972123459233955, "(5, 2, 9)": 0.6094591362578726, "(5, 2, 10)": 0.510204826612186, "(5, 3, 1)": 0.785237320471171, "(5, 3, 2)": 0.4266224490226538, "(5, 3, 3)": 0.8284028951714997, "(5, 3, 4)": 0.6009789379587214, "(5, 3, 5)": 0.4169949472498091, "(5, 3, 6)": 0.28667212543524934, "(5, 3, 7)": 0.3662443412777403, "(5, 3, 8)": 0.6941963359436043, "(5, 3, 9)": 0.27048782624377155, "(5, 3, 10)": 0.868068753105037, "(5, 4, 1)": 0.17061383807119182, "(5, 4, 2)": 0.82246653347851, "(5, 4, 3)": 0.5778635526768484, "(5, 4, 4)": 0.17705585020452208, "(5, 4, 5)": 0.782078847920882, "(5, 4, 6)": 0.5319027640155654, "(5, 4, 7)": 0.24249224563560842, "(5, 4, 8)": 0.6282505184601932, "(5, 4, 9)": 0.4787674091303834, "(5, 4, 10)": 0.6737497648550491, "(5, 6, 1)": 0.2219398370399528, "(5, 6, 2)": 0.6514625304965567, "(5, 6, 3)": 0.3751759483672177, "(5, 6, 4)": 0.2882059904537747, "(5, 6, 5)": 0.34808512407154146, "(5, 6, 6)": 0.14637511790738833, "(5, 6, 7)": 0.6018564828673002, "(5, 6, 8)": 0.15901182596967242, "(5, 6, 9)": 0.21265740415024192, "(5, 6, 10)": 0.32284734172125085, "(5, 7, 1)": 0.4069099032965481, "(5, 7, 2)": 0.36308100825602974, "(5, 7, 3)": 0.3326036383936838, "(5, 7, 4)": 0.30558250076903437, "(5, 7, 5)": 0.45336173007140046, "(5, 7, 6)": 0.35904858546694574, "(5, 7, 7)": 0.4910232686955659, "(5, 7, 8)": 0.40610426409314593, "(5, 7, 9)": 0.5457814319269765, "(5, 7, 10)": 0.6526416163110303, "(5, 8, 1)": 0.21205621235637173, "(5, 8, 2)": 0.20610166733063215, "(5, 8, 3)": 0.8584463388086364, "(5, 8, 4)": 0.5328733562050056, "(5, 8, 5)": 0.8760635409866532, "(5, 8, 6)": 0.10176201853373962, "(5, 8, 7)": 0.4571081532926179, "(5, 8, 8)": 0.25505920132894017, "(5, 8, 9)": 0.33835743467367907, "(5, 8, 10)": 0.5420973156821407, "(5, 9, 1)": 0.16309717409755448, "(5, 9, 2)": 0.1087816057862888, "(5, 9, 3)": 0.8872627311678959, "(5, 9, 4)": 0.566941672520918, "(5, 9, 5)": 0.5746615281593094, "(5, 9, 6)": 0.6484939472491682, "(5, 9, 7)": 0.4713795600119728, "(5, 9, 8)": 0.31659497404215187, "(5, 9, 9)": 0.5948335952828704, "(5, 9, 10)": 0.32137491999843903, "(5, 10, 1)": 0.2722746614739469, "(5, 10, 2)": 0.8409188165920835, "(5, 10, 3)": 0.3760664674760096, "(5, 10, 4)": 0.5556550125345494, "(5, 10, 5)": 0.541670225925897, "(5, 10, 6)": 0.7251938273168798, "(5, 10, 7)": 0.7508143374289746, "(5, 10, 8)": 0.4185863659735036, "(5, 10, 9)": 0.5841152996881783, "(5, 10, 10)": 0.7708081955099675, "(6, 1, 1)": 0.6711146649161631, "(6, 1, 2)": 0.7021937302963042, "(6, 1, 3)": 0.2277580941593713, "(6, 1, 4)": 0.27769878250771685, "(6, 1, 5)": 0.7416859676236226, "(6, 1, 6)": 0.45959852529107836, "(6, 1, 7)": 0.46775586998449814, "(6, 1, 8)": 0.31057419362716665, "(6, 1, 9)": 0.8432100019323427, "(6, 1, 10)": 0.3462027905221383, "(6, 2, 1)": 0.779010678330033, "(6, 2, 2)": 0.1942363511243544, "(6, 2, 3)": 0.35844197866781824, "(6, 2, 4)": 0.8055059801561003, "(6, 2, 5)": 0.4832383673069456, "(6, 2, 6)": 0.7760397723370371, "(6, 2, 7)": 0.4216083404451668, "(6, 2, 8)": 0.23632367517487998, "(6, 2, 9)": 0.4540009449453526, "(6, 2, 10)": 0.424605952423175, "(6, 3, 1)": 0.45796014307047084, "(6, 3, 2)": 0.5006667083055307, "(6, 3, 3)": 0.1240511191015302, "(6, 3, 4)": 0.6808072562065381, "(6, 3, 5)": 0.4228740636442868, "(6, 3, 6)": 0.5703806330611897, "(6, 3, 7)": 0.6253704932965812, "(6, 3, 8)": 0.37220486604108916, "(6, 3, 9)": 0.6166575295350554, "(6, 3, 10)": 0.172173798266061, "(6, 4, 1)": 0.7596259027985414, "(6, 4, 2)": 0.5687453736092668, "(6, 4, 3)": 0.2598705366342758, "(6, 4, 4)": 0.7024056658400205, "(6, 4, 5)": 0.5019439209427019, "(6, 4, 6)": 0.3052861921162762, "(6, 4, 7)": 0.7423159598578097, "(6, 4, 8)": 0.38916174059616393, "(6, 4, 9)": 0.42995555480603054, "(6, 4, 10)": 0.4840692514329764, "(6, 5, 1)": 0.5062017524807916, "(6, 5, 2)": 0.717745595344026, "(6, 5, 3)": 0.19011527530595693, "(6, 5, 4)": 0.8665796835064015, "(6, 5, 5)": 0.10326408811169162, "(6, 5, 6)": 0.7037031600989881, "(6, 5, 7)": 0.17487943575722503, "(6, 5, 8)": 0.15642668922622294, "(6, 5, 9)": 0.5183839722757576, "(6, 5, 10)": 0.6794212966399223, "(6, 7, 1)": 0.7538609122325166, "(6, 7, 2)": 0.8367593518480158, "(6, 7, 3)": 0.14312811958562177, "(6, 7, 4)": 0.15853091885236026, "(6, 7, 5)": 0.8061320182554025, "(6, 7, 6)": 0.4255285857814942, "(6, 7, 7)": 0.5800108479290221, "(6, 7, 8)": 0.3531928210016838, "(6, 7, 9)": 0.8989323851173011, "(6, 7, 10)": 0.6179229743509312, "(6, 8, 1)": 0.1247173235034592, "(6, 8, 2)": 0.4420407831085924, "(6, 8, 3)": 0.12854198059347885, "(6, 8, 4)": 0.46691098831289735, "(6, 8, 5)": 0.7732934698049121, "(6, 8, 6)": 0.3391641672814456, "(6, 8, 7)": 0.2597462186250783, "(6, 8, 8)": 0.5970567567493894, "(6, 8, 9)": 0.4739609251023119, "(6, 8, 10)": 0.5398320084378398, "(6, 9, 1)": 0.6922115597839666, "(6, 9, 2)": 0.26425283102510405, "(6, 9, 3)": 0.7348374893669544, "(6, 9, 4)": 0.4820777477558804, "(6, 9, 5)": 0.7415146220734419, "(6, 9, 6)": 0.597956745692742, "(6, 9, 7)": 0.32101886319008277, "(6, 9, 8)": 0.8404003933037059, "(6, 9, 9)": 0.10088545033411825, "(6, 9, 10)": 0.2486530015376457, "(6, 10, 1)": 0.8556283007447948, "(6, 10, 2)": 0.38157474439466565, "(6, 10, 3)": 0.3820990397045708, "(6, 10, 4)": 0.8351476585296577, "(6, 10, 5)": 0.23959196640005792, "(6, 10, 6)": 0.3437104229453818, "(6, 10, 7)": 0.6296999944649635, "(6, 10, 8)": 0.5205613875256667, "(6, 10, 9)": 0.1640548164414768, "(6, 10, 10)": 0.447503120239355, "(7, 1, 1)": 0.41105892512868913, "(7, 1, 2)": 0.6031444299608344, "(7, 1, 3)": 0.508997357285036, "(7, 1, 4)": 0.7326741158217336, "(7, 1, 5)": 0.4656097076731548, "(7, 1, 6)": 0.5196408255208721, "(7, 1, 7)": 0.23477991887076943, "(7, 1, 8)": 0.4047711135085934, "(7, 1, 9)": 0.5567853229374727, "(7, 1, 10)": 0.6078998295033285, "(7, 2, 1)": 0.5676156470771067, "(7, 2, 2)": 0.5527033697000683, "(7, 2, 3)": 0.8707973995012924, "(7, 2, 4)": 0.5954393325100432, "(7, 2, 5)": 0.6664813580990946, "(7, 2, 6)": 0.8052520804083031, "(7, 2, 7)": 0.2305761136113402, "(7, 2, 8)": 0.7516703228343194, "(7, 2, 9)": 0.2783703773833131, "(7, 2, 10)": 0.11400666518408027, "(7, 3, 1)": 0.3914469451973098, "(7, 3, 2)": 0.5806487475196803, "(7, 3, 3)": 0.7048551768036909, "(7, 3, 4)": 0.8799314454125574, "(7, 3, 5)": 0.1940823192860612, "(7, 3, 6)": 0.5666101144508188, "(7, 3, 7)": 0.685487063538983, "(7, 3, 8)": 0.45586651741196493, "(7, 3, 9)": 0.26164080639422044, "(7, 3, 10)": 0.8436038786102903, "(7, 4, 1)": 0.5856717019933851, "(7, 4, 2)": 0.6275666898687262, "(7, 4, 3)": 0.7700398248080201, "(7, 4, 4)": 0.5942737822606355, "(7, 4, 5)": 0.6531996050950064, "(7, 4, 6)": 0.17283221951310185, "(7, 4, 7)": 0.6777487330268415, "(7, 4, 8)": 0.6531102600062983, "(7, 4, 9)": 0.6961825496098587, "(7, 4, 10)": 0.10407672255365857, "(7, 5, 1)": 0.1765563912814213, "(7, 5, 2)": 0.3552336539272758, "(7, 5, 3)": 0.26226006056271833, "(7, 5, 4)": 0.29608175943554127, "(7, 5, 5)": 0.8333505058986462, "(7, 5, 6)": 0.1595079618378752, "(7, 5, 7)": 0.550018754178564, "(7, 5, 8)": 0.6585916858478588, "(7, 5, 9)": 0.11986080472953393, "(7, 5, 10)": 0.21787234100665068, "(7, 6, 1)": 0.10316569506493112, "(7, 6, 2)": 0.8854712337976943, "(7, 6, 3)": 0.11876301099326368, "(7, 6, 4)": 0.14368456334655627, "(7, 6, 5)": 0.18639553682892737, "(7, 6, 6)": 0.5183583384435436, "(7, 6, 7)": 0.413971285806193, "(7, 6, 8)": 0.879575611382332, "(7, 6, 9)": 0.7790429216678074, "(7, 6, 10)": 0.26303648086847425, "(7, 8, 1)": 0.28450489502741805, "(7, 8, 2)": 0.8994539798454408, "(7, 8, 3)": 0.5511552273674266, "(7, 8, 4)": 0.29274104386141564, "(7, 8, 5)": 0.8168853731554098, "(7, 8, 6)": 0.7355212120325048, "(7, 8, 7)": 0.4522606704929184, "(7, 8, 8)": 0.7913134485510794, "(7, 8, 9)": 0.3781040276152896, "(7, 8, 10)": 0.3807261202689902, "(7, 9, 1)": 0.44912967430027917, "(7, 9, 2)": 0.8962516512706428, "(7, 9, 3)": 0.6077889787947941, "(7, 9, 4)": 0.819920239192889, "(7, 9, 5)": 0.35381124998166713, "(7, 9, 6)": 0.10771522869148652, "(7, 9, 7)": 0.5404437276950318, "(7, 9, 8)": 0.19694952915450845, "(7, 9, 9)": 0.3608415869546593, "(7, 9, 10)": 0.8453865548206558, "(7, 10, 1)": 0.6875356521556518, "(7, 10, 2)": 0.3093248722057319, "(7, 10, 3)": 0.47046135099178465, "(7, 10, 4)": 0.7877217887304913, "(7, 10, 5)": 0.32192403269813463, "(7, 10, 6)": 0.1365061215257229, "(7, 10, 7)": 0.20059960364054172, "(7, 10, 8)": 0.26480562439346605, "(7, 10, 9)": 0.8100557523571424, "(7, 10, 10)": 0.6192684583250255, "(8, 1, 1)": 0.47696604452392266, "(8, 1, 2)": 0.1581171318506833, "(8, 1, 3)": 0.48030093643933336, "(8, 1, 4)": 0.5404589174976764, "(8, 1, 5)": 0.49479737852109884, "(8, 1, 6)": 0.8398103624044405, "(8, 1, 7)": 0.507373214335528, "(8, 1, 8)": 0.5028170610565035, "(8, 1, 9)": 0.18990979674907207, "(8, 1, 10)": 0.84780780015064, "(8, 2, 1)": 0.46042505606775974, "(8, 2, 2)": 0.38455357968577686, "(8, 2, 3)": 0.711482673477961, "(8, 2, 4)": 0.5605235120738095, "(8, 2, 5)": 0.8794264014564707, "(8, 2, 6)": 0.7702030527800665, "(8, 2, 7)": 0.7636221302928193, "(8, 2, 8)": 0.4099283841152527, "(8, 2, 9)": 0.64870070587723, "(8, 2, 10)": 0.42094245352792004, "(8, 3, 1)": 0.7563974061543978, "(8, 3, 2)": 0.7372372718859876, "(8, 3, 3)": 0.8942676966139713, "(8, 3, 4)": 0.7693010359818306, "(8, 3, 5)": 0.5096059726487452, "(8, 3, 6)": 0.3136015451440639, "(8, 3, 7)": 0.8459457910146341, "(8, 3, 8)": 0.7892084360348945, "(8, 3, 9)": 0.3072324830195031, "(8, 3, 10)": 0.5605877386675123, "(8, 4, 1)": 0.5363275898603231, "(8, 4, 2)": 0.5039972589972164, "(8, 4, 3)": 0.43777829605393825, "(8, 4, 4)": 0.4052715391389946, "(8, 4, 5)": 0.5036746771515802, "(8, 4, 6)": 0.3162708756342707, "(8, 4, 7)": 0.17506972090895234, "(8, 4, 8)": 0.13900613170385956, "(8, 4, 9)": 0.8062299579095303, "(8, 4, 10)": 0.11767113161009686, "(8, 5, 1)": 0.8014355128105571, "(8, 5, 2)": 0.22631481748795626, "(8, 5, 3)": 0.11045230456733766, "(8, 5, 4)": 0.8027631158618734, "(8, 5, 5)": 0.6413150197212437, "(8, 5, 6)": 0.1636333027159293, "(8, 5, 7)": 0.7933031516167016, "(8, 5, 8)": 0.6136401044968119, "(8, 5, 9)": 0.4690381531578173, "(8, 5, 10)": 0.7129365754311858, "(8, 6, 1)": 0.5561841255483038, "(8, 6, 2)": 0.47795160916135826, "(8, 6, 3)": 0.4226458814054088, "(8, 6, 4)": 0.3330556302669947, "(8, 6, 5)": 0.6643489336750007, "(8, 6, 6)": 0.46655333020693257, "(8, 6, 7)": 0.555069844625969, "(8, 6, 8)": 0.8380187735615418, "(8, 6, 9)": 0.4737537172914752, "(8, 6, 10)": 0.7578163053349564, "(8, 7, 1)": 0.2701114938630618, "(8, 7, 2)": 0.44449176572877613, "(8, 7, 3)": 0.731025568010857, "(8, 7, 4)": 0.27375274748177303, "(8, 7, 5)": 0.36846792199385003, "(8, 7, 6)": 0.6127754521936898, "(8, 7, 7)": 0.7008969110670615, "(8, 7, 8)": 0.7288102386434007, "(8, 7, 9)": 0.40396873494671737, "(8, 7, 10)": 0.6140067709569695, "(8, 9, 1)": 0.7934003885800979, "(8, 9, 2)": 0.41873303370963655, "(8, 9, 3)": 0.757633733231874, "(8, 9, 4)": 0.7666329768838737, "(8, 9, 5)": 0.4038516186239468, "(8, 9, 6)": 0.4948843776632129, "(8, 9, 7)": 0.7988401508428663, "(8, 9, 8)": 0.6869374059064739, "(8, 9, 9)": 0.2630463090325146, "(8, 9, 10)": 0.7034341569086048, "(8, 10, 1)": 0.6707986117468188, "(8, 10, 2)": 0.4255800793440586, "(8, 10, 3)": 0.7825253663405177, "(8, 10, 4)": 0.335715782285007, "(8, 10, 5)": 0.22697801230321035, "(8, 10, 6)": 0.8155491252217372, "(8, 10, 7)": 0.8645652127349809, "(8, 10, 8)": 0.8246858541029158, "(8, 10, 9)": 0.36567887053594894, "(8, 10, 10)": 0.30561758718952947, "(9, 1, 1)": 0.20244589725150208, "(9, 1, 2)": 0.45728392215169655, "(9, 1, 3)": 0.7374108479610729, "(9, 1, 4)": 0.5366004247663341, "(9, 1, 5)": 0.8326780745123886, "(9, 1, 6)": 0.6173235243908224, "(9, 1, 7)": 0.6747628612137968, "(9, 1, 8)": 0.14054013333159343, "(9, 1, 9)": 0.21983258202666925, "(9, 1, 10)": 0.14130583512681305, "(9, 2, 1)": 0.2476712439224789, "(9, 2, 2)": 0.19102262919443885, "(9, 2, 3)": 0.2084817086548889, "(9, 2, 4)": 0.432767736356066, "(9, 2, 5)": 0.45728592114140865, "(9, 2, 6)": 0.2466384879110197, "(9, 2, 7)": 0.7669257851568739, "(9, 2, 8)": 0.15200453270561481, "(9, 2, 9)": 0.8104089819287555, "(9, 2, 10)": 0.2985230285430698, "(9, 3, 1)": 0.7427992601478749, "(9, 3, 2)": 0.7574231662184098, "(9, 3, 3)": 0.5516722071342653, "(9, 3, 4)": 0.18514403703423987, "(9, 3, 5)": 0.28934493852946075, "(9, 3, 6)": 0.29144859137054163, "(9, 3, 7)": 0.2633804138708792, "(9, 3, 8)": 0.32892788660240635, "(9, 3, 9)": 0.5263573076456868, "(9, 3, 10)": 0.45473991710097816, "(9, 4, 1)": 0.7154819030374892, "(9, 4, 2)": 0.10955334884928636, "(9, 4, 3)": 0.6430459680024243, "(9, 4, 4)": 0.3029467436049522, "(9, 4, 5)": 0.3318968067334759, "(9, 4, 6)": 0.39478087250168536, "(9, 4, 7)": 0.5972401574788063, "(9, 4, 8)": 0.7783375829134023, "(9, 4, 9)": 0.6413824369773585, "(9, 4, 10)": 0.6176243419476951, "(9, 5, 1)": 0.5620134553729471, "(9, 5, 2)": 0.6552445502858993, "(9, 5, 3)": 0.7936267046765358, "(9, 5, 4)": 0.23469898782309678, "(9, 5, 5)": 0.1928978385445128, "(9, 5, 6)": 0.2765610623570572, "(9, 5, 7)": 0.8096596639125664, "(9, 5, 8)": 0.46719014119729996, "(9, 5, 9)": 0.2536647201667416, "(9, 5, 10)": 0.3992410932824918, "(9, 6, 1)": 0.7098010648407402, "(9, 6, 2)": 0.661825513957668, "(9, 6, 3)": 0.569230508455654, "(9, 6, 4)": 0.6237012792625511, "(9, 6, 5)": 0.6200788498820727, "(9, 6, 6)": 0.22184335579531594, "(9, 6, 7)": 0.5934796993717087, "(9, 6, 8)": 0.40673289488448483, "(9, 6, 9)": 0.44482172625250105, "(9, 6, 10)": 0.2571656022276512, "(9, 7, 1)": 0.54159702739073, "(9, 7, 2)": 0.7195674063078945, "(9, 7, 3)": 0.17873230251558578, "(9, 7, 4)": 0.2769468105916505, "(9, 7, 5)": 0.5843323055327923, "(9, 7, 6)": 0.6932066958586369, "(9, 7, 7)": 0.38697212225613986, "(9, 7, 8)": 0.6195609310241792, "(9, 7, 9)": 0.3464648440263166, "(9, 7, 10)": 0.625073687522016, "(9, 8, 1)": 0.7722191214141149, "(9, 8, 2)": 0.1889940660897617, "(9, 8, 3)": 0.4204201018803121, "(9, 8, 4)": 0.33957204920999084, "(9, 8, 5)": 0.3630614515627463, "(9, 8, 6)": 0.3913488731487864, "(9, 8, 7)": 0.6836339446508826, "(9, 8, 8)": 0.8712570178691944, "(9, 8, 9)": 0.28773397547194524, "(9, 8, 10)": 0.7358864231868347, "(9, 10, 1)": 0.3552877706863278, "(9, 10, 2)": 0.30472367470884465, "(9, 10, 3)": 0.26096431683706844, "(9, 10, 4)": 0.3449481960859007, "(9, 10, 5)": 0.49287021433939626, "(9, 10, 6)": 0.13540403088798403, "(9, 10, 7)": 0.8988806152285779, "(9, 10, 8)": 0.8473607941147048, "(9, 10, 9)": 0.3538314444358689, "(9, 10, 10)": 0.5719888853386945, "(10, 1, 1)": 0.17421671974646183, "(10, 1, 2)": 0.6164225713435957, "(10, 1, 3)": 0.7176448722354805, "(10, 1, 4)": 0.38502722898888175, "(10, 1, 5)": 0.7930686033020736, "(10, 1, 6)": 0.6447518627616627, "(10, 1, 7)": 0.2857310483716671, "(10, 1, 8)": 0.4968335668085351, "(10, 1, 9)": 0.7016118411644242, "(10, 1, 10)": 0.3684574836801503, "(10, 2, 1)": 0.607657236735254, "(10, 2, 2)": 0.2725801882040939, "(10, 2, 3)": 0.5783856275846418, "(10, 2, 4)": 0.8175583818125213, "(10, 2, 5)": 0.6699139946855028, "(10, 2, 6)": 0.33006850906261126, "(10, 2, 7)": 0.7671392524322314, "(10, 2, 8)": 0.5472399403771592, "(10, 2, 9)": 0.17219680133897847, "(10, 2, 10)": 0.7184708711277937, "(10, 3, 1)": 0.27280341406596065, "(10, 3, 2)": 0.8757260925921605, "(10, 3, 3)": 0.2446431565649573, "(10, 3, 4)": 0.28660602516091, "(10, 3, 5)": 0.666622816200009, "(10, 3, 6)": 0.79359655326283, "(10, 3, 7)": 0.7559894182242631, "(10, 3, 8)": 0.5115154898323603, "(10, 3, 9)": 0.8149053223177355, "(10, 3, 10)": 0.7209472939234204, "(10, 4, 1)": 0.21211017975947338, "(10, 4, 2)": 0.8142624583149657, "(10, 4, 3)": 0.8356528191512214, "(10, 4, 4)": 0.5218065368367614, "(10, 4, 5)": 0.648277102029597, "(10, 4, 6)": 0.7028149966060964, "(10, 4, 7)": 0.3636468120070572, "(10, 4, 8)": 0.6593716657084516, "(10, 4, 9)": 0.8473619282825255, "(10, 4, 10)": 0.2973786196061744, "(10, 5, 1)": 0.6559983541013756, "(10, 5, 2)": 0.3418574592941053, "(10, 5, 3)": 0.13869052812681942, "(10, 5, 4)": 0.4882622155582498, "(10, 5, 5)": 0.53323364875252, "(10, 5, 6)": 0.8428478301398405, "(10, 5, 7)": 0.36515295314369023, "(10, 5, 8)": 0.4075894846708261, "(10, 5, 9)": 0.4427486754972435, "(10, 5, 10)": 0.6301056004646962, "(10, 6, 1)": 0.32777228411831316, "(10, 6, 2)": 0.40821183637163927, "(10, 6, 3)": 0.36316168321777786, "(10, 6, 4)": 0.8289138730246585, "(10, 6, 5)": 0.4094017317249009, "(10, 6, 6)": 0.4020113160226747, "(10, 6, 7)": 0.216350250705755, "(10, 6, 8)": 0.5772936813902373, "(10, 6, 9)": 0.689742978159144, "(10, 6, 10)": 0.69581616104637, "(10, 7, 1)": 0.4858709821591283, "(10, 7, 2)": 0.41630417990029545, "(10, 7, 3)": 0.3237251062237434, "(10, 7, 4)": 0.49100011860473214, "(10, 7, 5)": 0.7142419914707724, "(10, 7, 6)": 0.799482266844945, "(10, 7, 7)": 0.5833355363581018, "(10, 7, 8)": 0.1122732547707332, "(10, 7, 9)": 0.6899962520763624, "(10, 7, 10)": 0.8773078086505744, "(10, 8, 1)": 0.8277355254938045, "(10, 8, 2)": 0.7983040702660705, "(10, 8, 3)": 0.629132693521625, "(10, 8, 4)": 0.186369334025967, "(10, 8, 5)": 0.3560419466515201, "(10, 8, 6)": 0.5410729059893626, "(10, 8, 7)": 0.1315167475904631, "(10, 8, 8)": 0.4764291856212578, "(10, 8, 9)": 0.11145713379381439, "(10, 8, 10)": 0.1913472565111768, "(10, 9, 1)": 0.89971223618876, "(10, 9, 2)": 0.4577082927419722, "(10, 9, 3)": 0.7367061396829542, "(10, 9, 4)": 0.8155994368104448, "(10, 9, 5)": 0.5922203914961581, "(10, 9, 6)": 0.36790159995963245, "(10, 9, 7)": 0.6845031874033254, "(10, 9, 8)": 0.5226615813508133, "(10, 9, 9)": 0.27134687604596963, "(10, 9, 10)": 0.20124006144210754}, "Lambd": {"((1, 2), 1)": 73, "((1, 2), 2)": 58, "((1, 2), 3)": 50, "((1, 2), 4)": 51, "((1, 2), 5)": 78, "((1, 2), 6)": 83, "((1, 2), 7)": 58, "((1, 2), 8)": 68, "((1, 2), 9)": 65, "((1, 2), 10)": 55, "((1, 3), 1)": 77, "((1, 3), 2)": 51, "((1, 3), 3)": 85, "((1, 3), 4)": 69, "((1, 3), 5)": 61, "((1, 3), 6)": 62, "((1, 3), 7)": 68, "((1, 3), 8)": 65, "((1, 3), 9)": 78, "((1, 3), 10)": 62, "((1, 4), 1)": 54, "((1, 4), 2)": 50, "((1, 4), 3)": 83, "((1, 4), 4)": 58, "((1, 4), 5)": 58, "((1, 4), 6)": 55, "((1, 4), 7)": 62, "((1, 4), 8)": 80, "((1, 4), 9)": 70, "((1, 4), 10)": 82, "((1, 5), 1)": 63, "((1, 5), 2)": 75, "((1, 5), 3)": 84, "((1, 5), 4)": 56, "((1, 5), 5)": 73, "((1, 5), 6)": 75, "((1, 5), 7)": 79, "((1, 5), 8)": 66, "((1, 5), 9)": 80, "((1, 5), 10)": 70, "((1, 6), 1)": 56, "((1, 6), 2)": 81, "((1, 6), 3)": 70, "((1, 6), 4)": 55, "((1, 6), 5)": 85, "((1, 6), 6)": 75, "((1, 6), 7)": 56, "((1, 6), 8)": 50, "((1, 6), 9)": 62, "((1, 6), 10)": 76, "((1, 7), 1)": 57, "((1, 7), 2)": 62, "((1, 7), 3)": 77, "((1, 7), 4)": 84, "((1, 7), 5)": 53, "((1, 7), 6)": 64, "((1, 7), 7)": 50, "((1, 7), 8)": 69, "((1, 7), 9)": 84, "((1, 7), 10)": 64, "((1, 8), 1)": 60, "((1, 8), 2)": 61, "((1, 8), 3)": 76, "((1, 8), 4)": 78, "((1, 8), 5)": 62, "((1, 8), 6)": 74, "((1, 8), 7)": 64, "((1, 8), 8)": 60, "((1, 8), 9)": 57, "((1, 8), 10)": 71, "((1, 9), 1)": 65, "((1, 9), 2)": 56, "((1, 9), 3)": 78, "((1, 9), 4)": 59, "((1, 9), 5)": 76, "((1, 9), 6)": 52, "((1, 9), 7)": 69, "((1, 9), 8)": 81, "((1, 9), 9)": 81, "((1, 9), 10)": 52, "((1, 10), 1)": 71, "((1, 10), 2)": 75, "((1, 10), 3)": 80, "((1, 10), 4)": 85, "((1, 10), 5)": 71, "((1, 10), 6)": 83, "((1, 10), 7)": 57, "((1, 10), 8)": 57, "((1, 10), 9)": 59, "((1, 10), 10)": 63, "((2, 3), 1)": 69, "((2, 3), 2)": 74, "((2, 3), 3)": 72, "((2, 3), 4)": 74, "((2, 3), 5)": 50, "((2, 3), 6)": 53, "((2, 3), 7)": 58, "((2, 3), 8)": 75, "((2, 3), 9)": 63, "((2, 3), 10)": 81, "((2, 4), 1)": 50, "((2, 4), 2)": 59, "((2, 4), 3)": 53, "((2, 4), 4)": 65, "((2, 4), 5)": 65, "((2, 4), 6)": 61, "((2, 4), 7)": 57, "((2, 4), 8)": 73, "((2, 4), 9)": 79, "((2, 4), 10)": 57, "((2, 5), 1)": 73, "((2, 5), 2)": 78, "((2, 5), 3)": 50, "((2, 5), 4)": 66, "((2, 5), 5)": 55, "((2, 5), 6)": 82, "((2, 5), 7)": 58, "((2, 5), 8)": 54, "((2, 5), 9)": 82, "((2, 5), 10)": 58, "((2, 6), 1)": 56, "((2, 6), 2)": 77, "((2, 6), 3)": 53, "((2, 6), 4)": 83, "((2, 6), 5)": 79, "((2, 6), 6)": 71, "((2, 6), 7)": 73, "((2, 6), 8)": 81, "((2, 6), 9)": 80, "((2, 6), 10)": 72, "((2, 7), 1)": 52, "((2, 7), 2)": 50, "((2, 7), 3)": 63, "((2, 7), 4)": 81, "((2, 7), 5)": 52, "((2, 7), 6)": 56, "((2, 7), 7)": 81, "((2, 7), 8)": 50, "((2, 7), 9)": 75, "((2, 7), 10)": 56, "((2, 8), 1)": 75, "((2, 8), 2)": 85, "((2, 8), 3)": 61, "((2, 8), 4)": 69, "((2, 8), 5)": 53, "((2, 8), 6)": 74, "((2, 8), 7)": 83, "((2, 8), 8)": 59, "((2, 8), 9)": 83, "((2, 8), 10)": 61, "((2, 9), 1)": 54, "((2, 9), 2)": 53, "((2, 9), 3)": 65, "((2, 9), 4)": 50, "((2, 9), 5)": 61, "((2, 9), 6)": 56, "((2, 9), 7)": 72, "((2, 9), 8)": 50, "((2, 9), 9)": 59, "((2, 9), 10)": 62, "((2, 10), 1)": 78, "((2, 10), 2)": 57, "((2, 10), 3)": 71, "((2, 10), 4)": 66, "((2, 10), 5)": 59, "((2, 10), 6)": 85, "((2, 10), 7)": 54, "((2, 10), 8)": 80, "((2, 10), 9)": 58, "((2, 10), 10)": 76, "((3, 4), 1)": 70, "((3, 4), 2)": 74, "((3, 4), 3)": 67, "((3, 4), 4)": 76, "((3, 4), 5)": 72, "((3, 4), 6)": 83, "((3, 4), 7)": 76, "((3, 4), 8)": 63, "((3, 4), 9)": 67, "((3, 4), 10)": 60, "((3, 5), 1)": 76, "((3, 5), 2)": 64, "((3, 5), 3)": 53, "((3, 5), 4)": 73, "((3, 5), 5)": 57, "((3, 5), 6)": 55, "((3, 5), 7)": 79, "((3, 5), 8)": 71, "((3, 5), 9)": 74, "((3, 5), 10)": 79, "((3, 6), 1)": 51, "((3, 6), 2)": 69, "((3, 6), 3)": 51, "((3, 6), 4)": 66, "((3, 6), 5)": 64, "((3, 6), 6)": 76, "((3, 6), 7)": 80, "((3, 6), 8)": 56, "((3, 6), 9)": 78, "((3, 6), 10)": 81, "((3, 7), 1)": 83, "((3, 7), 2)": 65, "((3, 7), 3)": 68, "((3, 7), 4)": 73, "((3, 7), 5)": 85, "((3, 7), 6)": 67, "((3, 7), 7)": 80, "((3, 7), 8)": 83, "((3, 7), 9)": 74, "((3, 7), 10)": 72, "((3, 8), 1)": 82, "((3, 8), 2)": 84, "((3, 8), 3)": 75, "((3, 8), 4)": 77, "((3, 8), 5)": 64, "((3, 8), 6)": 58, "((3, 8), 7)": 59, "((3, 8), 8)": 77, "((3, 8), 9)": 83, "((3, 8), 10)": 85, "((3, 9), 1)": 50, "((3, 9), 2)": 70, "((3, 9), 3)": 55, "((3, 9), 4)": 75, "((3, 9), 5)": 63, "((3, 9), 6)": 71, "((3, 9), 7)": 84, "((3, 9), 8)": 70, "((3, 9), 9)": 52, "((3, 9), 10)": 61, "((3, 10), 1)": 82, "((3, 10), 2)": 69, "((3, 10), 3)": 72, "((3, 10), 4)": 73, "((3, 10), 5)": 68, "((3, 10), 6)": 61, "((3, 10), 7)": 50, "((3, 10), 8)": 73, "((3, 10), 9)": 82, "((3, 10), 10)": 73, "((4, 5), 1)": 70, "((4, 5), 2)": 77, "((4, 5), 3)": 70, "((4, 5), 4)": 77, "((4, 5), 5)": 84, "((4, 5), 6)": 57, "((4, 5), 7)": 85, "((4, 5), 8)": 84, "((4, 5), 9)": 65, "((4, 5), 10)": 75, "((4, 6), 1)": 74, "((4, 6), 2)": 56, "((4, 6), 3)": 54, "((4, 6), 4)": 57, "((4, 6), 5)": 61, "((4, 6), 6)": 79, "((4, 6), 7)": 80, "((4, 6), 8)": 63, "((4, 6), 9)": 81, "((4, 6), 10)": 61, "((4, 7), 1)": 72, "((4, 7), 2)": 65, "((4, 7), 3)": 68, "((4, 7), 4)": 56, "((4, 7), 5)": 77, "((4, 7), 6)": 50, "((4, 7), 7)": 70, "((4, 7), 8)": 67, "((4, 7), 9)": 85, "((4, 7), 10)": 63, "((4, 8), 1)": 84, "((4, 8), 2)": 58, "((4, 8), 3)": 65, "((4, 8), 4)": 58, "((4, 8), 5)": 70, "((4, 8), 6)": 50, "((4, 8), 7)": 59, "((4, 8), 8)": 74, "((4, 8), 9)": 73, "((4, 8), 10)": 82, "((4, 9), 1)": 63, "((4, 9), 2)": 81, "((4, 9), 3)": 71, "((4, 9), 4)": 78, "((4, 9), 5)": 55, "((4, 9), 6)": 51, "((4, 9), 7)": 70, "((4, 9), 8)": 78, "((4, 9), 9)": 69, "((4, 9), 10)": 75, "((4, 10), 1)": 84, "((4, 10), 2)": 71, "((4, 10), 3)": 50, "((4, 10), 4)": 69, "((4, 10), 5)": 56, "((4, 10), 6)": 61, "((4, 10), 7)": 82, "((4, 10), 8)": 77, "((4, 10), 9)": 82, "((4, 10), 10)": 75, "((5, 6), 1)": 84, "((5, 6), 2)": 73, "((5, 6), 3)": 50, "((5, 6), 4)": 61, "((5, 6), 5)": 55, "((5, 6), 6)": 78, "((5, 6), 7)": 67, "((5, 6), 8)": 54, "((5, 6), 9)": 79, "((5, 6), 10)": 81, "((5, 7), 1)": 63, "((5, 7), 2)": 79, "((5, 7), 3)": 65, "((5, 7), 4)": 56, "((5, 7), 5)": 82, "((5, 7), 6)": 52, "((5, 7), 7)": 76, "((5, 7), 8)": 77, "((5, 7), 9)": 74, "((5, 7), 10)": 81, "((5, 8), 1)": 51, "((5, 8), 2)": 66, "((5, 8), 3)": 53, "((5, 8), 4)": 76, "((5, 8), 5)": 60, "((5, 8), 6)": 64, "((5, 8), 7)": 67, "((5, 8), 8)": 73, "((5, 8), 9)": 76, "((5, 8), 10)": 54, "((5, 9), 1)": 84, "((5, 9), 2)": 54, "((5, 9), 3)": 60, "((5, 9), 4)": 78, "((5, 9), 5)": 74, "((5, 9), 6)": 53, "((5, 9), 7)": 81, "((5, 9), 8)": 68, "((5, 9), 9)": 71, "((5, 9), 10)": 67, "((5, 10), 1)": 76, "((5, 10), 2)": 70, "((5, 10), 3)": 77, "((5, 10), 4)": 84, "((5, 10), 5)": 81, "((5, 10), 6)": 82, "((5, 10), 7)": 85, "((5, 10), 8)": 68, "((5, 10), 9)": 81, "((5, 10), 10)": 62, "((6, 7), 1)": 50, "((6, 7), 2)": 63, "((6, 7), 3)": 82, "((6, 7), 4)": 81, "((6, 7), 5)": 53, "((6, 7), 6)": 51, "((6, 7), 7)": 77, "((6, 7), 8)": 81, "((6, 7), 9)": 69, "((6, 7), 10)": 77, "((6, 8), 1)": 65, "((6, 8), 2)": 70, "((6, 8), 3)": 59, "((6, 8), 4)": 72, "((6, 8), 5)": 70, "((6, 8), 6)": 50, "((6, 8), 7)": 73, "((6, 8), 8)": 77, "((6, 8), 9)": 80, "((6, 8), 10)": 69, "((6, 9), 1)": 55, "((6, 9), 2)": 77, "((6, 9), 3)": 67, "((6, 9), 4)": 55, "((6, 9), 5)": 55, "((6, 9), 6)": 74, "((6, 9), 7)": 71, "((6, 9), 8)": 62, "((6, 9), 9)": 50, "((6, 9), 10)": 82, "((6, 10), 1)": 56, "((6, 10), 2)": 80, "((6, 10), 3)": 63, "((6, 10), 4)": 77, "((6, 10), 5)": 69, "((6, 10), 6)": 77, "((6, 10), 7)": 85, "((6, 10), 8)": 78, "((6, 10), 9)": 78, "((6, 10), 10)": 76, "((7, 8), 1)": 72, "((7, 8), 2)": 60, "((7, 8), 3)": 52, "((7, 8), 4)": 62, "((7, 8), 5)": 60, "((7, 8), 6)": 59, "((7, 8), 7)": 55, "((7, 8), 8)": 52, "((7, 8), 9)": 85, "((7, 8), 10)": 50, "((7, 9), 1)": 68, "((7, 9), 2)": 78, "((7, 9), 3)": 54, "((7, 9), 4)": 79, "((7, 9), 5)": 71, "((7, 9), 6)": 79, "((7, 9), 7)": 72, "((7, 9), 8)": 67, "((7, 9), 9)": 53, "((7, 9), 10)": 61, "((7, 10), 1)": 67, "((7, 10), 2)": 80, "((7, 10), 3)": 71, "((7, 10), 4)": 84, "((7, 10), 5)": 70, "((7, 10), 6)": 61, "((7, 10), 7)": 84, "((7, 10), 8)": 59, "((7, 10), 9)": 84, "((7, 10), 10)": 65, "((8, 9), 1)": 65, "((8, 9), 2)": 59, "((8, 9), 3)": 75, "((8, 9), 4)": 59, "((8, 9), 5)": 79, "((8, 9), 6)": 79, "((8, 9), 7)": 80, "((8, 9), 8)": 68, "((8, 9), 9)": 84, "((8, 9), 10)": 78, "((8, 10), 1)": 71, "((8, 10), 2)": 63, "((8, 10), 3)": 56, "((8, 10), 4)": 60, "((8, 10), 5)": 81, "((8, 10), 6)": 78, "((8, 10), 7)": 63, "((8, 10), 8)": 71, "((8, 10), 9)": 83, "((8, 10), 10)": 66, "((9, 10), 1)": 68, "((9, 10), 2)": 69, "((9, 10), 3)": 61, "((9, 10), 4)": 68, "((9, 10), 5)": 72, "((9, 10), 6)": 77, "((9, 10), 7)": 71, "((9, 10), 8)": 56, "((9, 10), 9)": 80, "((9, 10), 10)": 70}, "E": {"1": {}, "2": {}, "3": {}, "4": {}, "5": {}, "6": {}, "7": {}, "8": {}, "9": {}, "10": {}}, "R": {"(1, 2, 1)": [[1, 4], [2, 4]], "(1, 2, 2)": [[1, 5], [5, 10], [2, 10]], "(1, 2, 3)": [[1, 7], [5, 7], [2, 5]], "(1, 3, 1)": [[1, 4], [3, 4]], "(1, 3, 2)": [[1, 9], [5, 9], [3, 5]], "(1, 3, 3)": [[1, 5], [5, 6], [6, 7], [3, 7]], "(1, 4, 1)": [[1, 2], [2, 4]], "(1, 4, 2)": [[1, 7], [7, 10], [4, 10]], "(1, 4, 3)": [[1, 7], [5, 7], [4, 5]], "(1, 5, 1)": [[1, 6], [5, 6]], "(1, 5, 2)": [[1, 2], [2, 5]], "(1, 5, 3)": [[1, 6], [6, 7], [5, 7]], "(1, 6, 1)": [[1, 7], [6, 7]], "(1, 6, 2)": [[1, 10], [7, 10], [6, 7]], "(1, 6, 3)": [[1, 8], [8, 9], [7, 9], [6, 7]], "(1, 7, 1)": [[1, 3], [3, 7]], "(1, 7, 2)": [[1, 6], [6, 7]], "(1, 7, 3)": [[1, 9], [5, 9], [5, 7]], "(1, 8, 1)": [[1, 3], [3, 8]], "(1, 8, 2)": [[1, 7], [4, 7], [4, 8]], "(1, 8, 3)": [[1, 9], [4, 9], [3, 4], [3, 8]], "(1, 9, 1)": [[1, 5], [5, 9]], "(1, 9, 2)": [[1, 6], [6, 9]], "(1, 9, 3)": [[1, 7], [3, 7], [3, 4], [4, 9]], "(1, 10, 1)": [[1, 2], [2, 10]], "(1, 10, 2)": [[1, 8], [4, 8], [4, 10]], "(1, 10, 3)": [[1, 6], [6, 10]], "(2, 1, 1)": [[2, 3], [1, 3]], "(2, 1, 2)": [[2, 5], [1, 5]], "(2, 1, 3)": [[2, 3], [3, 10], [1, 10]], "(2, 3, 1)": [[2, 4], [3, 4]], "(2, 3, 2)": [[2, 5], [3, 5]], "(2, 3, 3)": [[2, 4], [4, 10], [3, 10]], "(2, 4, 1)": [[2, 3], [3, 4]], "(2, 4, 2)": [[2, 3], [1, 3], [1, 4]], "(2, 4, 3)": [[2, 5], [1, 5], [1, 4]], "(2, 5, 1)": [[2, 7], [5, 7]], "(2, 5, 2)": [[2, 9], [5, 9]], "(2, 5, 3)": [[1, 2], [1, 9], [5, 9]], "(2, 6, 1)": [[1, 2], [1, 6]], "(2, 6, 2)": [[2, 3], [1, 3], [1, 6]], "(2, 6, 3)": [[2, 9], [5, 9], [5, 7], [6, 7]], "(2, 7, 1)": [[1, 2], [1, 7]], "(2, 7, 2)": [[2, 8], [1, 8], [1, 7]], "(2, 7, 3)": [[2, 8], [8, 9], [4, 9], [4, 7]], "(2, 8, 1)": [[2, 4], [3, 4], [3, 8]], "(2, 8, 2)": [[2, 6], [6, 8]], "(2, 8, 3)": [[2, 10], [4, 10], [1, 4], [1, 8]], "(2, 9, 1)": [[2, 10], [9, 10]], "(2, 9, 2)": [[2, 4], [4, 9]], "(2, 9, 3)": [[2, 10], [1, 10], [1, 9]], "(2, 10, 1)": [[2, 4], [4, 10]], "(2, 10, 2)": [[2, 6], [6, 10]], "(2, 10, 3)": [[2, 8], [4, 8], [4, 10]], "(3, 1, 1)": [[3, 7], [1, 7]], "(3, 1, 2)": [[3, 9], [1, 9]], "(3, 1, 3)": [[2, 3], [2, 4], [1, 4]], "(3, 2, 1)": [[3, 9], [2, 9]], "(3, 2, 2)": [[3, 8], [5, 8], [2, 5]], "(3, 2, 3)": [[3, 9], [8, 9], [2, 8]], "(3, 4, 1)": [[3, 10], [4, 10]], "(3, 4, 2)": [[3, 9], [4, 9]], "(3, 4, 3)": [[1, 3], [1, 8], [4, 8]], "(3, 5, 1)": [[3, 8], [5, 8]], "(3, 5, 2)": [[3, 6], [5, 6]], "(3, 5, 3)": [[3, 4], [4, 5]], "(3, 6, 1)": [[3, 4], [4, 6]], "(3, 6, 2)": [[3, 8], [1, 8], [1, 6]], "(3, 6, 3)": [[3, 8], [4, 8], [4, 10], [6, 10]], "(3, 7, 1)": [[3, 9], [7, 9]], "(3, 7, 2)": [[3, 10], [7, 10]], "(3, 7, 3)": [[3, 5], [5, 7]], "(3, 8, 1)": [[3, 5], [5, 8]], "(3, 8, 2)": [[1, 3], [1, 8]], "(3, 8, 3)": [[3, 7], [7, 10], [8, 10]], "(3, 9, 1)": [[3, 10], [9, 10]], "(3, 9, 2)": [[3, 5], [5, 9]], "(3, 9, 3)": [[3, 6], [4, 6], [4, 9]], "(3, 10, 1)": [[3, 8], [8, 10]], "(3, 10, 2)": [[3, 9], [9, 10]], "(3, 10, 3)": [[3, 5], [5, 10]], "(4, 1, 1)": [[3, 4], [1, 3]], "(4, 1, 2)": [[4, 7], [7, 10], [1, 10]], "(4, 1, 3)": [[4, 9], [5, 9], [1, 5]], "(4, 2, 1)": [[4, 10], [2, 10]], "(4, 2, 2)": [[4, 5], [2, 5]], "(4, 2, 3)": [[4, 8], [6, 8], [2, 6]], "(4, 3, 1)": [[4, 10], [3, 10]], "(4, 3, 2)": [[2, 4], [2, 3]], "(4, 3, 3)": [[2, 4], [2, 9], [3, 9]], "(4, 5, 1)": [[4, 6], [5, 6]], "(4, 5, 2)": [[1, 4], [1, 5]], "(4, 5, 3)": [[4, 7], [7, 9], [5, 9]], "(4, 6, 1)": [[4, 7], [6, 7]], "(4, 6, 2)": [[1, 4], [1, 6]], "(4, 6, 3)": [[4, 5], [2, 5], [2, 6]], "(4, 7, 1)": [[3, 4], [3, 7]], "(4, 7, 2)": [[4, 10], [7, 10]], "(4, 7, 3)": [[4, 8], [2, 8], [2, 7]], "(4, 8, 1)": [[4, 5], [5, 8]], "(4, 8, 2)": [[2, 4], [2, 5], [5, 8]], "(4, 8, 3)": [[4, 9], [1, 9], [1, 8]], "(4, 9, 1)": [[3, 4], [3, 9]], "(4, 9, 2)": [[4, 8], [8, 9]], "(4, 9, 3)": [[4, 6], [6, 9]], "(4, 10, 1)": [[4, 9], [9, 10]], "(4, 10, 2)": [[4, 6], [6, 7], [7, 10]], "(4, 10, 3)": [[1, 4], [1, 3], [3, 9], [9, 10]], "(5, 1, 1)": [[5, 8], [3, 8], [3, 7], [1, 7]], "(5, 1, 2)": [[5, 6], [3, 6], [1, 3]], "(5, 1, 3)": [[5, 10], [1, 10]], "(5, 2, 1)": [[5, 9], [2, 9]], "(5, 2, 2)": [[5, 9], [9, 10], [2, 10]], "(5, 2, 3)": [[1, 5], [1, 3], [2, 3]], "(5, 3, 1)": [[5, 8], [3, 8]], "(5, 3, 2)": [[5, 7], [3, 7]], "(5, 3, 3)": [[2, 5], [2, 3]], "(5, 4, 1)": [[5, 8], [4, 8]], "(5, 4, 2)": [[5, 7], [4, 7]], "(5, 4, 3)": [[3, 5], [3, 6], [6, 7], [4, 7]], "(5, 6, 1)": [[3, 5], [3, 6]], "(5, 6, 2)": [[5, 7], [4, 7], [3, 4], [3, 6]], "(5, 6, 3)": [[5, 10], [9, 10], [6, 9]], "(5, 7, 1)": [[1, 5], [1, 7]], "(5, 7, 2)": [[5, 9], [9, 10], [7, 10]], "(5, 7, 3)": [[1, 5], [1, 6], [6, 7]], "(5, 8, 1)": [[5, 7], [7, 8]], "(5, 8, 2)": [[5, 9], [8, 9]], "(5, 8, 3)": [[5, 7], [7, 9], [4, 9], [4, 8]], "(5, 9, 1)": [[5, 7], [7, 9]], "(5, 9, 2)": [[2, 5], [2, 7], [7, 9]], "(5, 9, 3)": [[5, 6], [6, 7], [2, 7], [2, 9]], "(5, 10, 1)": [[3, 5], [3, 10]], "(5, 10, 2)": [[5, 7], [7, 10]], "(5, 10, 3)": [[2, 5], [2, 8], [8, 10]], "(6, 1, 1)": [[3, 6], [1, 3]], "(6, 1, 2)": [[6, 9], [1, 9]], "(6, 1, 3)": [[6, 10], [7, 10], [1, 7]], "(6, 2, 1)": [[4, 6], [2, 4]], "(6, 2, 2)": [[3, 6], [2, 3]], "(6, 2, 3)": [[3, 6], [3, 9], [2, 9]], "(6, 3, 1)": [[1, 6], [1, 3]], "(6, 3, 2)": [[2, 6], [2, 7], [3, 7]], "(6, 3, 3)": [[6, 7], [7, 8], [3, 8]], "(6, 4, 1)": [[5, 6], [4, 5]], "(6, 4, 2)": [[2, 6], [2, 3], [3, 4]], "(6, 4, 3)": [[6, 9], [2, 9], [2, 4]], "(6, 5, 1)": [[4, 6], [3, 4], [3, 5]], "(6, 5, 2)": [[6, 7], [5, 7]], "(6, 5, 3)": [[6, 9], [5, 9]], "(6, 7, 1)": [[5, 6], [5, 7]], "(6, 7, 2)": [[1, 6], [1, 7]], "(6, 7, 3)": [[6, 10], [1, 10], [1, 7]], "(6, 8, 1)": [[6, 9], [8, 9]], "(6, 8, 2)": [[6, 7], [4, 7], [4, 8]], "(6, 8, 3)": [[5, 6], [2, 5], [2, 8]], "(6, 9, 1)": [[3, 6], [3, 9]], "(6, 9, 2)": [[2, 6], [2, 9]], "(6, 9, 3)": [[1, 6], [1, 4], [4, 7], [7, 9]], "(6, 10, 1)": [[4, 6], [4, 10]], "(6, 10, 2)": [[3, 6], [3, 10]], "(6, 10, 3)": [[6, 7], [7, 10]], "(7, 1, 1)": [[7, 10], [9, 10], [1, 9]], "(7, 1, 2)": [[3, 7], [3, 5], [1, 5]], "(7, 1, 3)": [[6, 7], [1, 6]], "(7, 2, 1)": [[4, 7], [2, 4]], "(7, 2, 2)": [[1, 7], [1, 2]], "(7, 2, 3)": [[1, 7], [1, 3], [2, 3]], "(7, 3, 1)": [[7, 9], [3, 9]], "(7, 3, 2)": [[7, 10], [4, 10], [3, 4]], "(7, 3, 3)": [[5, 7], [3, 5]], "(7, 4, 1)": [[7, 8], [4, 8]], "(7, 4, 2)": [[7, 8], [8, 10], [4, 10]], "(7, 4, 3)": [[6, 7], [6, 10], [4, 10]], "(7, 5, 1)": [[7, 8], [5, 8]], "(7, 5, 2)": [[1, 7], [1, 5]], "(7, 5, 3)": [[7, 9], [2, 9], [2, 5]], "(7, 6, 1)": [[5, 7], [5, 6]], "(7, 6, 2)": [[1, 7], [1, 6]], "(7, 6, 3)": [[3, 7], [3, 10], [6, 10]], "(7, 8, 1)": [[1, 7], [1, 8]], "(7, 8, 2)": [[7, 9], [3, 9], [3, 8]], "(7, 8, 3)": [[4, 7], [1, 4], [1, 8]], "(7, 9, 1)": [[2, 7], [2, 9]], "(7, 9, 2)": [[4, 7], [4, 9]], "(7, 9, 3)": [[3, 7], [3, 10], [9, 10]], "(7, 10, 1)": [[2, 7], [2, 10]], "(7, 10, 2)": [[5, 7], [5, 10]], "(7, 10, 3)": [[7, 9], [5, 9], [3, 5], [3, 10]], "(8, 1, 1)": [[5, 8], [1, 5]], "(8, 1, 2)": [[7, 8], [1, 7]], "(8, 1, 3)": [[8, 10], [3, 10], [1, 3]], "(8, 2, 1)": [[5, 8], [2, 5]], "(8, 2, 2)": [[5, 8], [4, 5], [2, 4]], "(8, 2, 3)": [[4, 8], [4, 7], [5, 7], [2, 5]], "(8, 3, 1)": [[8, 9], [3, 9]], "(8, 3, 2)": [[1, 8], [1, 9], [3, 9]], "(8, 3, 3)": [[5, 8], [5, 6], [1, 6], [1, 3]], "(8, 4, 1)": [[6, 8], [4, 6]], "(8, 4, 2)": [[7, 8], [4, 7]], "(8, 4, 3)": [[8, 10], [7, 10], [4, 7]], "(8, 5, 1)": [[3, 8], [3, 5]], "(8, 5, 2)": [[1, 8], [1, 5]], "(8, 5, 3)": [[7, 8], [3, 7], [3, 10], [5, 10]], "(8, 6, 1)": [[4, 8], [4, 6]], "(8, 6, 2)": [[7, 8], [6, 7]], "(8, 6, 3)": [[2, 8], [2, 6]], "(8, 7, 1)": [[8, 9], [7, 9]], "(8, 7, 2)": [[6, 8], [6, 9], [7, 9]], "(8, 7, 3)": [[3, 8], [1, 3], [1, 10], [7, 10]], "(8, 9, 1)": [[3, 8], [3, 9]], "(8, 9, 2)": [[6, 8], [6, 9]], "(8, 9, 3)": [[5, 8], [4, 5], [1, 4], [1, 9]], "(8, 10, 1)": [[6, 8], [6, 10]], "(8, 10, 2)": [[6, 8], [6, 7], [7, 10]], "(8, 10, 3)": [[4, 8], [1, 4], [1, 10]], "(9, 1, 1)": [[4, 9], [1, 4]], "(9, 1, 2)": [[6, 9], [6, 8], [1, 8]], "(9, 1, 3)": [[5, 9], [4, 5], [2, 4], [1, 2]], "(9, 2, 1)": [[1, 9], [1, 2]], "(9, 2, 2)": [[6, 9], [2, 6]], "(9, 2, 3)": [[6, 9], [1, 6], [1, 2]], "(9, 3, 1)": [[9, 10], [3, 10]], "(9, 3, 2)": [[9, 10], [2, 10], [2, 3]], "(9, 3, 3)": [[5, 9], [4, 5], [3, 4]], "(9, 4, 1)": [[8, 9], [4, 8]], "(9, 4, 2)": [[6, 9], [4, 6]], "(9, 4, 3)": [[5, 9], [4, 5]], "(9, 5, 1)": [[1, 9], [1, 5]], "(9, 5, 2)": [[9, 10], [5, 10]], "(9, 5, 3)": [[6, 9], [1, 6], [1, 5]], "(9, 6, 1)": [[7, 9], [6, 7]], "(9, 6, 2)": [[8, 9], [6, 8]], "(9, 6, 3)": [[5, 9], [5, 7], [2, 7], [2, 6]], "(9, 7, 1)": [[8, 9], [7, 8]], "(9, 7, 2)": [[3, 9], [3, 8], [7, 8]], "(9, 7, 3)": [[9, 10], [6, 10], [6, 8], [7, 8]], "(9, 8, 1)": [[7, 9], [7, 8]], "(9, 8, 2)": [[2, 9], [2, 10], [8, 10]], "(9, 8, 3)": [[6, 9], [3, 6], [3, 5], [5, 8]], "(9, 10, 1)": [[5, 9], [5, 10]], "(9, 10, 2)": [[8, 9], [6, 8], [6, 10]], "(9, 10, 3)": [[4, 9], [1, 4], [1, 10]], "(10, 1, 1)": [[9, 10], [1, 9]], "(10, 1, 2)": [[3, 10], [1, 3]], "(10, 1, 3)": [[7, 10], [4, 7], [1, 4]], "(10, 2, 1)": [[6, 10], [4, 6], [2, 4]], "(10, 2, 2)": [[5, 10], [2, 5]], "(10, 2, 3)": [[9, 10], [5, 9], [2, 5]], "(10, 3, 1)": [[4, 10], [3, 4]], "(10, 3, 2)": [[8, 10], [5, 8], [4, 5], [3, 4]], "(10, 3, 3)": [[1, 10], [1, 4], [3, 4]], "(10, 4, 1)": [[7, 10], [4, 7]], "(10, 4, 2)": [[9, 10], [4, 9]], "(10, 4, 3)": [[3, 10], [3, 5], [5, 9], [4, 9]], "(10, 5, 1)": [[2, 10], [2, 5]], "(10, 5, 2)": [[6, 10], [6, 8], [5, 8]], "(10, 5, 3)": [[9, 10], [2, 9], [2, 5]], "(10, 6, 1)": [[4, 10], [4, 5], [5, 6]], "(10, 6, 2)": [[1, 10], [1, 6]], "(10, 6, 3)": [[2, 10], [1, 2], [1, 6]], "(10, 7, 1)": [[4, 10], [4, 7]], "(10, 7, 2)": [[2, 10], [1, 2], [1, 7]], "(10, 7, 3)": [[5, 10], [5, 7]], "(10, 8, 1)": [[6, 10], [6, 8]], "(10, 8, 2)": [[3, 10], [3, 9], [8, 9]], "(10, 8, 3)": [[6, 10], [3, 6], [3, 9], [8, 9]], "(10, 9, 1)": [[4, 10], [4, 9]], "(10, 9, 2)": [[4, 10], [4, 8], [8, 9]], "(10, 9, 3)": [[6, 10], [6, 8], [8, 9]]}}